[{"sleepStartTimestampGMT":"2021-07-27T03:48:00.0","sleepEndTimestampGMT":"2021-07-27T12:44:00.0","calendarDate":"2021-07-27","sleepWindowConfirmationType":"ENHANCED_CONFIRMED_FINAL","deepSleepSeconds":2520,"lightSleepSeconds":16440,"remSleepSeconds":12480,"awakeSleepSeconds":720,"unmeasurableSeconds":0,"spo2SleepSummary":{"userProfilePk":1520967,"deviceId":3359304790,"sleepMeasurementStartGMT":"2021-07-27T03:49:00.0","sleepMeasurementEndGMT":"2021-07-27T11:24:00.0","averageSPO2":94.0,"averageHR":51.0,"lowestSPO2":86},"averageRespiration":14.0,"lowestRespiration":9.0,"highestRespiration":22.0,"retro":false},{"sleepStartTimestampGMT":"2021-07-28T04:01:00.0","sleepEndTimestampGMT":"2021-07-28T12:35:00.0","calendarDate":"2021-07-28","sleepWindowConfirmationType":"ENHANCED_CONFIRMED_FINAL","deepSleepSeconds":3360,"lightSleepSeconds":17640,"remSleepSeconds":9420,"awakeSleepSeconds":420,"unmeasurableSeconds":0,"spo2SleepSummary":{"userProfilePk":1520967,"deviceId":3359304790,"sleepMeasurementStartGMT":"2021-07-28T04:02:00.0","sleepMeasurementEndGMT":"2021-07-28T11:24:00.0","averageSPO2":92.0,"averageHR":50.0,"lowestSPO2":83},"averageRespiration":15.0,"lowestRespiration":10.0,"highestRespiration":23.0,"retro":false},{"sleepStartTimestampGMT":"2021-07-29T04:29:00.0","sleepEndTimestampGMT":"2021-07-29T12:26:00.0","calendarDate":"2021-07-29","sleepWindowConfirmationType":"ENHANCED_CONFIRMED_FINAL","deepSleepSeconds":3600,"lightSleepSeconds":17460,"remSleepSeconds":7320,"awakeSleepSeconds":240,"unmeasurableSeconds":0,"spo2SleepSummary":{"userProfilePk":1520967,"deviceId":3359304790,"sleepMeasurementStartGMT":"2021-07-29T04:30:00.0","sleepMeasurementEndGMT":"2021-07-29T11:25:00.0","averageSPO2":93.0,"averageHR":51.0,"lowestSPO2":84},"averageRespiration":15.0,"lowestRespiration":12.0,"highestRespiration":20.0,"retro":false},{"sleepStartTimestampGMT":"2021-07-30T05:04:00.0","sleepEndTimestampGMT":"2021-07-30T12:16:00.0","calendarDate":"2021-07-30","sleepWindowConfirmationType":"ENHANCED_CONFIRMED_FINAL","deepSleepSeconds":2520,"lightSleepSeconds":19320,"remSleepSeconds":4080,"awakeSleepSeconds":0,"unmeasurableSeconds":0,"spo2SleepSummary":{"userProfilePk":1520967,"deviceId":3359304790,"sleepMeasurementStartGMT":"2021-07-30T05:05:00.0","sleepMeasurementEndGMT":"2021-07-30T11:25:00.0","averageSPO2":89.0,"averageHR":52.0,"lowestSPO2":85},"averageRespiration":14.0,"lowestRespiration":11.0,"highestRespiration":21.0,"retro":false},{"sleepStartTimestampGMT":"2021-07-31T03:50:00.0","sleepEndTimestampGMT":"2021-07-31T12:37:00.0","calendarDate":"2021-07-31","sleepWindowConfirmationType":"ENHANCED_CONFIRMED_FINAL","deepSleepSeconds":780,"lightSleepSeconds":21180,"remSleepSeconds":8640,"awakeSleepSeconds":1020,"unmeasurableSeconds":0,"spo2SleepSummary":{"userProfilePk":1520967,"deviceId":3359304790,"sleepMeasurementStartGMT":"2021-07-31T03:51:00.0","sleepMeasurementEndGMT":"2021-07-31T11:24:00.0","averageSPO2":90.0,"averageHR":48.0,"lowestSPO2":79},"averageRespiration":15.0,"lowestRespiration":9.0,"highestRespiration":23.0,"retro":false},{"sleepStartTimestampGMT":"2021-08-01T04:03:00.0","sleepEndTimestampGMT":"2021-08-01T13:23:00.0","calendarDate":"2021-08-01","sleepWindowConfirmationType":"ENHANCED_CONFIRMED_FINAL","deepSleepSeconds":1020,"lightSleepSeconds":23100,"remSleepSeconds":8760,"awakeSleepSeconds":720,"unmeasurableSeconds":0,"spo2SleepSummary":{"userProfilePk":1520967,"deviceId":3359304790,"sleepMeasurementStartGMT":"2021-08-01T04:04:00.0","sleepMeasurementEndGMT":"2021-08-01T11:25:00.0","averageSPO2":91.0,"averageHR":49.0,"lowestSPO2":84},"averageRespiration":14.0,"lowestRespiration":7.0,"highestRespiration":21.0,"retro":false},{"sleepStartTimestampGMT":"2021-08-02T04:50:00.0","sleepEndTimestampGMT":"2021-08-02T13:34:00.0","calendarDate":"2021-08-02","sleepWindowConfirmationType":"ENHANCED_CONFIRMED_FINAL","deepSleepSeconds":0,"lightSleepSeconds":22740,"remSleepSeconds":6540,"awakeSleepSeconds":2160,"unmeasurableSeconds":0,"spo2SleepSummary":{"userProfilePk":1520967,"deviceId":3359304790,"sleepMeasurementStartGMT":"2021-08-02T04:51:00.0","sleepMeasurementEndGMT":"2021-08-02T11:25:00.0","averageSPO2":92.0,"averageHR":57.0,"lowestSPO2":86},"averageRespiration":14.0,"lowestRespiration":9.0,"highestRespiration":21.0,"retro":false},{"sleepStartTimestampGMT":"2021-08-03T05:19:00.0","sleepEndTimestampGMT":"2021-08-03T13:51:00.0","calendarDate":"2021-08-03","sleepWindowConfirmationType":"ENHANCED_CONFIRMED_FINAL","deepSleepSeconds":1260,"lightSleepSeconds":21240,"remSleepSeconds":7860,"awakeSleepSeconds":360,"unmeasurableSeconds":0,"spo2SleepSummary":{"userProfilePk":1520967,"deviceId":3359304790,"sleepMeasurementStartGMT":"2021-08-03T05:20:00.0","sleepMeasurementEndGMT":"2021-08-03T11:24:00.0","averageSPO2":91.0,"averageHR":50.0,"lowestSPO2":86},"averageRespiration":15.0,"lowestRespiration":9.0,"highestRespiration":21.0,"retro":false},{"sleepStartTimestampGMT":"2021-08-04T03:35:00.0","sleepEndTimestampGMT":"2021-08-04T13:57:00.0","calendarDate":"2021-08-04","sleepWindowConfirmationType":"ENHANCED_CONFIRMED_FINAL","deepSleepSeconds":3000,"lightSleepSeconds":22980,"remSleepSeconds":10920,"awakeSleepSeconds":420,"unmeasurableSeconds":0,"spo2SleepSummary":{"userProfilePk":1520967,"deviceId":3359304790,"sleepMeasurementStartGMT":"2021-08-04T03:36:00.0","sleepMeasurementEndGMT":"2021-08-04T11:24:00.0","averageSPO2":92.0,"averageHR":50.0,"lowestSPO2":88},"averageRespiration":17.0,"lowestRespiration":9.0,"highestRespiration":24.0,"retro":false},{"sleepStartTimestampGMT":"2021-08-05T04:31:00.0","sleepEndTimestampGMT":"2021-08-05T12:47:00.0","calendarDate":"2021-08-05","sleepWindowConfirmationType":"ENHANCED_CONFIRMED_FINAL","deepSleepSeconds":540,"lightSleepSeconds":20760,"remSleepSeconds":7920,"awakeSleepSeconds":540,"unmeasurableSeconds":0,"spo2SleepSummary":{"userProfilePk":1520967,"deviceId":3359304790,"sleepMeasurementStartGMT":"2021-08-05T04:32:00.0","sleepMeasurementEndGMT":"2021-08-05T11:24:00.0","averageSPO2":90.0,"averageHR":49.0,"lowestSPO2":81},"averageRespiration":15.0,"lowestRespiration":9.0,"highestRespiration":22.0,"retro":false},{"sleepStartTimestampGMT":"2021-08-06T04:10:00.0","sleepEndTimestampGMT":"2021-08-06T13:12:00.0","calendarDate":"2021-08-06","sleepWindowConfirmationType":"ENHANCED_CONFIRMED_FINAL","deepSleepSeconds":300,"lightSleepSeconds":19740,"remSleepSeconds":11400,"awakeSleepSeconds":1080,"unmeasurableSeconds":0,"spo2SleepSummary":{"userProfilePk":1520967,"deviceId":3359304790,"sleepMeasurementStartGMT":"2021-08-06T04:11:00.0","sleepMeasurementEndGMT":"2021-08-06T11:25:00.0","averageSPO2":94.0,"averageHR":54.0,"lowestSPO2":86},"averageRespiration":14.0,"lowestRespiration":9.0,"highestRespiration":21.0,"retro":false},{"sleepStartTimestampGMT":"2021-08-07T04:25:00.0","sleepEndTimestampGMT":"2021-08-07T11:56:00.0","calendarDate":"2021-08-07","sleepWindowConfirmationType":"ENHANCED_CONFIRMED_FINAL","deepSleepSeconds":1200,"lightSleepSeconds":18960,"remSleepSeconds":6900,"awakeSleepSeconds":0,"unmeasurableSeconds":0,"spo2SleepSummary":{"userProfilePk":1520967,"deviceId":3359304790,"sleepMeasurementStartGMT":"2021-08-07T04:26:00.0","sleepMeasurementEndGMT":"2021-08-07T11:25:00.0","averageSPO2":92.0,"averageHR":52.0,"lowestSPO2":86},"averageRespiration":12.0,"lowestRespiration":8.0,"highestRespiration":20.0,"retro":false},{"sleepStartTimestampGMT":"2021-08-08T03:40:00.0","sleepEndTimestampGMT":"2021-08-08T14:28:00.0","calendarDate":"2021-08-08","sleepWindowConfirmationType":"ENHANCED_CONFIRMED_FINAL","deepSleepSeconds":1440,"lightSleepSeconds":24660,"remSleepSeconds":10980,"awakeSleepSeconds":1800,"unmeasurableSeconds":0,"spo2SleepSummary":{"userProfilePk":1520967,"deviceId":3359304790,"sleepMeasurementStartGMT":"2021-08-08T03:41:00.0","sleepMeasurementEndGMT":"2021-08-08T11:25:00.0","averageSPO2":92.0,"averageHR":51.0,"lowestSPO2":86},"averageRespiration":13.0,"lowestRespiration":9.0,"highestRespiration":18.0,"retro":false},{"sleepStartTimestampGMT":"2021-08-09T04:09:00.0","sleepEndTimestampGMT":"2021-08-09T12:33:00.0","calendarDate":"2021-08-09","sleepWindowConfirmationType":"ENHANCED_CONFIRMED_FINAL","deepSleepSeconds":1260,"lightSleepSeconds":20700,"remSleepSeconds":8280,"awakeSleepSeconds":0,"unmeasurableSeconds":0,"spo2SleepSummary":{"userProfilePk":1520967,"deviceId":3359304790,"sleepMeasurementStartGMT":"2021-08-09T04:10:00.0","sleepMeasurementEndGMT":"2021-08-09T11:25:00.0","averageSPO2":91.0,"averageHR":49.0,"lowestSPO2":83},"averageRespiration":15.0,"lowestRespiration":12.0,"highestRespiration":21.0,"retro":false},{"sleepStartTimestampGMT":"2021-08-10T03:33:00.0","sleepEndTimestampGMT":"2021-08-10T12:21:00.0","calendarDate":"2021-08-10","sleepWindowConfirmationType":"ENHANCED_CONFIRMED_FINAL","deepSleepSeconds":540,"lightSleepSeconds":22260,"remSleepSeconds":8460,"awakeSleepSeconds":420,"unmeasurableSeconds":0,"spo2SleepSummary":{"userProfilePk":1520967,"deviceId":3359304790,"sleepMeasurementStartGMT":"2021-08-10T03:34:00.0","sleepMeasurementEndGMT":"2021-08-10T11:25:00.0","averageSPO2":92.0,"averageHR":49.0,"lowestSPO2":85},"averageRespiration":13.0,"lowestRespiration":7.0,"highestRespiration":20.0,"retro":false},{"sleepStartTimestampGMT":"2021-08-11T03:52:00.0","sleepEndTimestampGMT":"2021-08-11T12:47:00.0","calendarDate":"2021-08-11","sleepWindowConfirmationType":"ENHANCED_CONFIRMED_FINAL","deepSleepSeconds":480,"lightSleepSeconds":20820,"remSleepSeconds":9480,"awakeSleepSeconds":1320,"unmeasurableSeconds":0,"spo2SleepSummary":{"userProfilePk":1520967,"deviceId":3359304790,"sleepMeasurementStartGMT":"2021-08-11T03:53:00.0","sleepMeasurementEndGMT":"2021-08-11T11:24:00.0","averageSPO2":93.0,"averageHR":51.0,"lowestSPO2":88},"averageRespiration":14.0,"lowestRespiration":8.0,"highestRespiration":21.0,"retro":false},{"sleepStartTimestampGMT":"2021-08-12T03:41:00.0","sleepEndTimestampGMT":"2021-08-12T12:30:00.0","calendarDate":"2021-08-12","sleepWindowConfirmationType":"ENHANCED_CONFIRMED_FINAL","deepSleepSeconds":1260,"lightSleepSeconds":19800,"remSleepSeconds":9900,"awakeSleepSeconds":780,"unmeasurableSeconds":0,"spo2SleepSummary":{"userProfilePk":1520967,"deviceId":3359304790,"sleepMeasurementStartGMT":"2021-08-12T03:42:00.0","sleepMeasurementEndGMT":"2021-08-12T11:24:00.0","averageSPO2":92.0,"averageHR":45.0,"lowestSPO2":82},"averageRespiration":15.0,"lowestRespiration":10.0,"highestRespiration":21.0,"retro":false},{"sleepStartTimestampGMT":"2021-08-13T04:39:00.0","sleepEndTimestampGMT":"2021-08-13T12:45:00.0","calendarDate":"2021-08-13","sleepWindowConfirmationType":"ENHANCED_CONFIRMED_FINAL","deepSleepSeconds":480,"lightSleepSeconds":19200,"remSleepSeconds":9480,"awakeSleepSeconds":0,"unmeasurableSeconds":0,"spo2SleepSummary":{"userProfilePk":1520967,"deviceId":3359304790,"sleepMeasurementStartGMT":"2021-08-13T04:40:00.0","sleepMeasurementEndGMT":"2021-08-13T11:24:00.0","averageSPO2":94.0,"averageHR":54.0,"lowestSPO2":90},"averageRespiration":15.0,"lowestRespiration":10.0,"highestRespiration":22.0,"retro":false},{"sleepStartTimestampGMT":"2021-08-14T03:52:00.0","sleepEndTimestampGMT":"2021-08-14T13:28:00.0","calendarDate":"2021-08-14","sleepWindowConfirmationType":"ENHANCED_CONFIRMED_FINAL","deepSleepSeconds":0,"lightSleepSeconds":24240,"remSleepSeconds":9120,"awakeSleepSeconds":1200,"unmeasurableSeconds":0,"spo2SleepSummary":{"userProfilePk":1520967,"deviceId":3359304790,"sleepMeasurementStartGMT":"2021-08-14T03:53:00.0","sleepMeasurementEndGMT":"2021-08-14T11:25:00.0","averageSPO2":93.0,"averageHR":52.0,"lowestSPO2":87},"averageRespiration":15.0,"lowestRespiration":10.0,"highestRespiration":22.0,"retro":false},{"sleepStartTimestampGMT":"2021-08-15T04:55:00.0","sleepEndTimestampGMT":"2021-08-15T14:06:00.0","calendarDate":"2021-08-15","sleepWindowConfirmationType":"ENHANCED_CONFIRMED_FINAL","deepSleepSeconds":1380,"lightSleepSeconds":23640,"remSleepSeconds":5400,"awakeSleepSeconds":2640,"unmeasurableSeconds":0,"spo2SleepSummary":{"userProfilePk":1520967,"deviceId":3359304790,"sleepMeasurementStartGMT":"2021-08-15T04:56:00.0","sleepMeasurementEndGMT":"2021-08-15T11:25:00.0","averageSPO2":94.0,"averageHR":52.0,"lowestSPO2":89},"averageRespiration":14.0,"lowestRespiration":10.0,"highestRespiration":20.0,"retro":false},{"sleepStartTimestampGMT":"2021-08-16T03:50:00.0","sleepEndTimestampGMT":"2021-08-16T12:25:00.0","calendarDate":"2021-08-16","sleepWindowConfirmationType":"ENHANCED_CONFIRMED_FINAL","deepSleepSeconds":1980,"lightSleepSeconds":17940,"remSleepSeconds":10980,"awakeSleepSeconds":0,"unmeasurableSeconds":0,"spo2SleepSummary":{"userProfilePk":1520967,"deviceId":3359304790,"sleepMeasurementStartGMT":"2021-08-16T03:51:00.0","sleepMeasurementEndGMT":"2021-08-16T11:25:00.0","averageSPO2":94.0,"averageHR":51.0,"lowestSPO2":90},"averageRespiration":15.0,"lowestRespiration":9.0,"highestRespiration":21.0,"retro":false},{"sleepStartTimestampGMT":"2021-08-17T03:48:00.0","sleepEndTimestampGMT":"2021-08-17T12:43:00.0","calendarDate":"2021-08-17","sleepWindowConfirmationType":"ENHANCED_CONFIRMED_FINAL","deepSleepSeconds":2640,"lightSleepSeconds":19380,"remSleepSeconds":8400,"awakeSleepSeconds":1680,"unmeasurableSeconds":0,"spo2SleepSummary":{"userProfilePk":1520967,"deviceId":3359304790,"sleepMeasurementStartGMT":"2021-08-17T03:49:00.0","sleepMeasurementEndGMT":"2021-08-17T11:25:00.0","averageSPO2":94.0,"averageHR":47.0,"lowestSPO2":87},"averageRespiration":16.0,"lowestRespiration":9.0,"highestRespiration":22.0,"retro":false},{"sleepStartTimestampGMT":"2021-08-18T03:55:00.0","sleepEndTimestampGMT":"2021-08-18T12:47:00.0","calendarDate":"2021-08-18","sleepWindowConfirmationType":"ENHANCED_CONFIRMED_FINAL","deepSleepSeconds":4620,"lightSleepSeconds":16200,"remSleepSeconds":10200,"awakeSleepSeconds":900,"unmeasurableSeconds":0,"spo2SleepSummary":{"userProfilePk":1520967,"deviceId":3359304790,"sleepMeasurementStartGMT":"2021-08-18T03:56:00.0","sleepMeasurementEndGMT":"2021-08-18T11:25:00.0","averageSPO2":93.0,"averageHR":47.0,"lowestSPO2":86},"averageRespiration":17.0,"lowestRespiration":13.0,"highestRespiration":25.0,"retro":false},{"sleepStartTimestampGMT":"2021-08-19T04:31:00.0","sleepEndTimestampGMT":"2021-08-19T12:25:00.0","calendarDate":"2021-08-19","sleepWindowConfirmationType":"ENHANCED_CONFIRMED_FINAL","deepSleepSeconds":1380,"lightSleepSeconds":20400,"remSleepSeconds":6240,"awakeSleepSeconds":420,"unmeasurableSeconds":0,"spo2SleepSummary":{"userProfilePk":1520967,"deviceId":3359304790,"sleepMeasurementStartGMT":"2021-08-19T04:32:00.0","sleepMeasurementEndGMT":"2021-08-19T11:25:00.0","averageSPO2":93.0,"averageHR":50.0,"lowestSPO2":87},"averageRespiration":15.0,"lowestRespiration":9.0,"highestRespiration":21.0,"retro":false},{"sleepStartTimestampGMT":"2021-08-20T03:27:00.0","sleepEndTimestampGMT":"2021-08-20T12:18:00.0","calendarDate":"2021-08-20","sleepWindowConfirmationType":"ENHANCED_CONFIRMED_FINAL","deepSleepSeconds":1560,"lightSleepSeconds":20820,"remSleepSeconds":9180,"awakeSleepSeconds":300,"unmeasurableSeconds":0,"spo2SleepSummary":{"userProfilePk":1520967,"deviceId":3359304790,"sleepMeasurementStartGMT":"2021-08-20T03:28:00.0","sleepMeasurementEndGMT":"2021-08-20T11:25:00.0","averageSPO2":93.0,"averageHR":48.0,"lowestSPO2":87},"averageRespiration":12.0,"lowestRespiration":6.0,"highestRespiration":19.0,"retro":false},{"sleepStartTimestampGMT":"2021-08-21T04:39:00.0","sleepEndTimestampGMT":"2021-08-21T13:37:00.0","calendarDate":"2021-08-21","sleepWindowConfirmationType":"ENHANCED_CONFIRMED_FINAL","deepSleepSeconds":600,"lightSleepSeconds":19740,"remSleepSeconds":11400,"awakeSleepSeconds":540,"unmeasurableSeconds":0,"spo2SleepSummary":{"userProfilePk":1520967,"deviceId":3359304790,"sleepMeasurementStartGMT":"2021-08-21T04:40:00.0","sleepMeasurementEndGMT":"2021-08-21T11:25:00.0","averageSPO2":94.0,"averageHR":50.0,"lowestSPO2":87},"averageRespiration":16.0,"lowestRespiration":9.0,"highestRespiration":23.0,"retro":false},{"sleepStartTimestampGMT":"2021-08-22T04:20:00.0","sleepEndTimestampGMT":"2021-08-22T13:52:00.0","calendarDate":"2021-08-22","sleepWindowConfirmationType":"ENHANCED_CONFIRMED_FINAL","deepSleepSeconds":1980,"lightSleepSeconds":21540,"remSleepSeconds":10140,"awakeSleepSeconds":660,"unmeasurableSeconds":0,"spo2SleepSummary":{"userProfilePk":1520967,"deviceId":3359304790,"sleepMeasurementStartGMT":"2021-08-22T04:21:00.0","sleepMeasurementEndGMT":"2021-08-22T11:25:00.0","averageSPO2":94.0,"averageHR":50.0,"lowestSPO2":90},"averageRespiration":15.0,"lowestRespiration":11.0,"highestRespiration":23.0,"retro":false},{"sleepStartTimestampGMT":"2021-08-23T03:57:00.0","sleepEndTimestampGMT":"2021-08-23T12:11:00.0","calendarDate":"2021-08-23","sleepWindowConfirmationType":"ENHANCED_CONFIRMED_FINAL","deepSleepSeconds":0,"lightSleepSeconds":17820,"remSleepSeconds":11520,"awakeSleepSeconds":300,"unmeasurableSeconds":0,"spo2SleepSummary":{"userProfilePk":1520967,"deviceId":3359304790,"sleepMeasurementStartGMT":"2021-08-23T03:58:00.0","sleepMeasurementEndGMT":"2021-08-23T11:25:00.0","averageSPO2":93.0,"averageHR":51.0,"lowestSPO2":87},"averageRespiration":16.0,"lowestRespiration":12.0,"highestRespiration":21.0,"retro":false},{"sleepStartTimestampGMT":"2021-08-24T03:55:00.0","sleepEndTimestampGMT":"2021-08-24T12:15:00.0","calendarDate":"2021-08-24","sleepWindowConfirmationType":"ENHANCED_CONFIRMED_FINAL","deepSleepSeconds":2940,"lightSleepSeconds":18360,"remSleepSeconds":7320,"awakeSleepSeconds":1380,"unmeasurableSeconds":0,"spo2SleepSummary":{"userProfilePk":1520967,"deviceId":3359304790,"sleepMeasurementStartGMT":"2021-08-24T03:56:00.0","sleepMeasurementEndGMT":"2021-08-24T11:25:00.0","averageSPO2":93.0,"averageHR":48.0,"lowestSPO2":87},"averageRespiration":15.0,"lowestRespiration":11.0,"highestRespiration":19.0,"retro":false},{"sleepStartTimestampGMT":"2021-08-25T04:46:00.0","sleepEndTimestampGMT":"2021-08-25T12:32:00.0","calendarDate":"2021-08-25","sleepWindowConfirmationType":"ENHANCED_CONFIRMED_FINAL","deepSleepSeconds":2100,"lightSleepSeconds":18420,"remSleepSeconds":6960,"awakeSleepSeconds":480,"unmeasurableSeconds":0,"spo2SleepSummary":{"userProfilePk":1520967,"deviceId":3359304790,"sleepMeasurementStartGMT":"2021-08-25T04:47:00.0","sleepMeasurementEndGMT":"2021-08-25T11:25:00.0","averageSPO2":93.0,"averageHR":49.0,"lowestSPO2":86},"averageRespiration":16.0,"lowestRespiration":11.0,"highestRespiration":22.0,"retro":false},{"sleepStartTimestampGMT":"2021-08-26T03:53:00.0","sleepEndTimestampGMT":"2021-08-26T12:28:00.0","calendarDate":"2021-08-26","sleepWindowConfirmationType":"ENHANCED_CONFIRMED_FINAL","deepSleepSeconds":2040,"lightSleepSeconds":17340,"remSleepSeconds":10680,"awakeSleepSeconds":840,"unmeasurableSeconds":0,"spo2SleepSummary":{"userProfilePk":1520967,"deviceId":3359304790,"sleepMeasurementStartGMT":"2021-08-26T03:54:00.0","sleepMeasurementEndGMT":"2021-08-26T11:25:00.0","averageSPO2":94.0,"averageHR":48.0,"lowestSPO2":89},"averageRespiration":14.0,"lowestRespiration":8.0,"highestRespiration":19.0,"retro":false},{"sleepStartTimestampGMT":"2021-08-27T04:02:00.0","sleepEndTimestampGMT":"2021-08-27T12:44:00.0","calendarDate":"2021-08-27","sleepWindowConfirmationType":"ENHANCED_CONFIRMED_FINAL","deepSleepSeconds":780,"lightSleepSeconds":20460,"remSleepSeconds":9360,"awakeSleepSeconds":720,"unmeasurableSeconds":0,"spo2SleepSummary":{"userProfilePk":1520967,"deviceId":3359304790,"sleepMeasurementStartGMT":"2021-08-27T04:03:00.0","sleepMeasurementEndGMT":"2021-08-27T11:25:00.0","averageSPO2":93.0,"averageHR":48.0,"lowestSPO2":89},"averageRespiration":15.0,"lowestRespiration":11.0,"highestRespiration":21.0,"retro":false},{"sleepStartTimestampGMT":"2021-08-28T05:28:00.0","sleepEndTimestampGMT":"2021-08-28T13:58:00.0","calendarDate":"2021-08-28","sleepWindowConfirmationType":"ENHANCED_CONFIRMED_FINAL","deepSleepSeconds":0,"lightSleepSeconds":21420,"remSleepSeconds":7860,"awakeSleepSeconds":1320,"unmeasurableSeconds":0,"spo2SleepSummary":{"userProfilePk":1520967,"deviceId":3359304790,"sleepMeasurementStartGMT":"2021-08-28T05:29:00.0","sleepMeasurementEndGMT":"2021-08-28T11:25:00.0","averageSPO2":94.0,"averageHR":51.0,"lowestSPO2":90},"averageRespiration":15.0,"lowestRespiration":11.0,"highestRespiration":21.0,"retro":false},{"sleepStartTimestampGMT":"2021-08-29T03:46:00.0","sleepEndTimestampGMT":"2021-08-29T12:41:00.0","calendarDate":"2021-08-29","sleepWindowConfirmationType":"ENHANCED_CONFIRMED_FINAL","deepSleepSeconds":2580,"lightSleepSeconds":19920,"remSleepSeconds":6360,"awakeSleepSeconds":3240,"unmeasurableSeconds":0,"spo2SleepSummary":{"userProfilePk":1520967,"deviceId":3359304790,"sleepMeasurementStartGMT":"2021-08-29T03:47:00.0","sleepMeasurementEndGMT":"2021-08-29T11:23:00.0","averageSPO2":94.0,"averageHR":52.0,"lowestSPO2":90},"averageRespiration":15.0,"lowestRespiration":11.0,"highestRespiration":20.0,"retro":false},{"sleepStartTimestampGMT":"2021-08-30T03:58:00.0","sleepEndTimestampGMT":"2021-08-30T12:28:00.0","calendarDate":"2021-08-30","sleepWindowConfirmationType":"ENHANCED_CONFIRMED_FINAL","deepSleepSeconds":420,"lightSleepSeconds":18540,"remSleepSeconds":10680,"awakeSleepSeconds":960,"unmeasurableSeconds":0,"spo2SleepSummary":{"userProfilePk":1520967,"deviceId":3359304790,"sleepMeasurementStartGMT":"2021-08-30T03:59:00.0","sleepMeasurementEndGMT":"2021-08-30T11:25:00.0","averageSPO2":94.0,"averageHR":50.0,"lowestSPO2":86},"averageRespiration":15.0,"lowestRespiration":10.0,"highestRespiration":21.0,"retro":false},{"sleepStartTimestampGMT":"2021-08-31T05:00:00.0","sleepEndTimestampGMT":"2021-08-31T12:59:00.0","calendarDate":"2021-08-31","sleepWindowConfirmationType":"ENHANCED_CONFIRMED_FINAL","deepSleepSeconds":2460,"lightSleepSeconds":16560,"remSleepSeconds":8880,"awakeSleepSeconds":840,"unmeasurableSeconds":0,"spo2SleepSummary":{"userProfilePk":1520967,"deviceId":3359304790,"sleepMeasurementStartGMT":"2021-08-31T05:01:00.0","sleepMeasurementEndGMT":"2021-08-31T11:25:00.0","averageSPO2":92.0,"averageHR":51.0,"lowestSPO2":85},"averageRespiration":16.0,"lowestRespiration":9.0,"highestRespiration":25.0,"retro":false},{"sleepStartTimestampGMT":"2021-09-01T03:56:00.0","sleepEndTimestampGMT":"2021-09-01T12:53:00.0","calendarDate":"2021-09-01","sleepWindowConfirmationType":"ENHANCED_CONFIRMED_FINAL","deepSleepSeconds":3240,"lightSleepSeconds":15900,"remSleepSeconds":13080,"awakeSleepSeconds":0,"unmeasurableSeconds":0,"spo2SleepSummary":{"userProfilePk":1520967,"deviceId":3359304790,"sleepMeasurementStartGMT":"2021-09-01T03:57:00.0","sleepMeasurementEndGMT":"2021-09-01T11:25:00.0","averageSPO2":94.0,"averageHR":47.0,"lowestSPO2":88},"averageRespiration":16.0,"lowestRespiration":11.0,"highestRespiration":24.0,"retro":false},{"sleepStartTimestampGMT":"2021-09-02T04:20:00.0","sleepEndTimestampGMT":"2021-09-02T12:40:00.0","calendarDate":"2021-09-02","sleepWindowConfirmationType":"ENHANCED_CONFIRMED_FINAL","deepSleepSeconds":0,"lightSleepSeconds":19440,"remSleepSeconds":9240,"awakeSleepSeconds":1320,"unmeasurableSeconds":0,"spo2SleepSummary":{"userProfilePk":1520967,"deviceId":3359304790,"sleepMeasurementStartGMT":"2021-09-02T04:21:00.0","sleepMeasurementEndGMT":"2021-09-02T11:25:00.0","averageSPO2":93.0,"averageHR":49.0,"lowestSPO2":88},"averageRespiration":15.0,"lowestRespiration":12.0,"highestRespiration":21.0,"retro":false},{"sleepStartTimestampGMT":"2021-09-03T04:50:00.0","sleepEndTimestampGMT":"2021-09-03T12:44:00.0","calendarDate":"2021-09-03","sleepWindowConfirmationType":"ENHANCED_CONFIRMED_FINAL","deepSleepSeconds":2640,"lightSleepSeconds":17040,"remSleepSeconds":7980,"awakeSleepSeconds":780,"unmeasurableSeconds":0,"spo2SleepSummary":{"userProfilePk":1520967,"deviceId":3359304790,"sleepMeasurementStartGMT":"2021-09-03T04:51:00.0","sleepMeasurementEndGMT":"2021-09-03T11:25:00.0","averageSPO2":93.0,"averageHR":47.0,"lowestSPO2":89},"averageRespiration":16.0,"lowestRespiration":9.0,"highestRespiration":22.0,"retro":false},{"sleepStartTimestampGMT":"2021-09-04T04:39:00.0","sleepEndTimestampGMT":"2021-09-04T13:47:00.0","calendarDate":"2021-09-04","sleepWindowConfirmationType":"ENHANCED_CONFIRMED_FINAL","deepSleepSeconds":0,"lightSleepSeconds":22440,"remSleepSeconds":10440,"awakeSleepSeconds":0,"unmeasurableSeconds":0,"spo2SleepSummary":{"userProfilePk":1520967,"deviceId":3359304790,"sleepMeasurementStartGMT":"2021-09-04T04:40:00.0","sleepMeasurementEndGMT":"2021-09-04T11:25:00.0","averageSPO2":94.0,"averageHR":51.0,"lowestSPO2":89},"averageRespiration":14.0,"lowestRespiration":10.0,"highestRespiration":20.0,"retro":false},{"sleepStartTimestampGMT":"2021-09-05T03:41:00.0","sleepEndTimestampGMT":"2021-09-05T12:59:00.0","calendarDate":"2021-09-05","sleepWindowConfirmationType":"ENHANCED_CONFIRMED_FINAL","deepSleepSeconds":1800,"lightSleepSeconds":21900,"remSleepSeconds":9480,"awakeSleepSeconds":300,"unmeasurableSeconds":0,"spo2SleepSummary":{"userProfilePk":1520967,"deviceId":3359304790,"sleepMeasurementStartGMT":"2021-09-05T03:42:00.0","sleepMeasurementEndGMT":"2021-09-05T11:24:00.0","averageSPO2":92.0,"averageHR":50.0,"lowestSPO2":86},"averageRespiration":16.0,"lowestRespiration":12.0,"highestRespiration":23.0,"retro":false},{"sleepStartTimestampGMT":"2021-09-06T04:13:00.0","sleepEndTimestampGMT":"2021-09-06T13:47:00.0","calendarDate":"2021-09-06","sleepWindowConfirmationType":"ENHANCED_CONFIRMED_FINAL","deepSleepSeconds":3480,"lightSleepSeconds":24300,"remSleepSeconds":4380,"awakeSleepSeconds":2280,"unmeasurableSeconds":0,"spo2SleepSummary":{"userProfilePk":1520967,"deviceId":3359304790,"sleepMeasurementStartGMT":"2021-09-06T04:14:00.0","sleepMeasurementEndGMT":"2021-09-06T11:24:00.0","averageSPO2":93.0,"averageHR":51.0,"lowestSPO2":88},"averageRespiration":15.0,"lowestRespiration":10.0,"highestRespiration":20.0,"retro":false},{"sleepStartTimestampGMT":"2021-09-07T04:16:00.0","sleepEndTimestampGMT":"2021-09-07T12:29:00.0","calendarDate":"2021-09-07","sleepWindowConfirmationType":"ENHANCED_CONFIRMED_FINAL","deepSleepSeconds":1380,"lightSleepSeconds":18840,"remSleepSeconds":7980,"awakeSleepSeconds":1380,"unmeasurableSeconds":0,"spo2SleepSummary":{"userProfilePk":1520967,"deviceId":3359304790,"sleepMeasurementStartGMT":"2021-09-07T04:17:00.0","sleepMeasurementEndGMT":"2021-09-07T11:24:00.0","averageSPO2":92.0,"averageHR":51.0,"lowestSPO2":85},"averageRespiration":15.0,"lowestRespiration":10.0,"highestRespiration":22.0,"retro":false},{"sleepStartTimestampGMT":"2021-09-08T05:06:00.0","sleepEndTimestampGMT":"2021-09-08T12:44:00.0","calendarDate":"2021-09-08","sleepWindowConfirmationType":"ENHANCED_CONFIRMED_FINAL","deepSleepSeconds":3060,"lightSleepSeconds":14640,"remSleepSeconds":9120,"awakeSleepSeconds":660,"unmeasurableSeconds":0,"spo2SleepSummary":{"userProfilePk":1520967,"deviceId":3359304790,"sleepMeasurementStartGMT":"2021-09-08T05:07:00.0","sleepMeasurementEndGMT":"2021-09-08T11:25:00.0","averageSPO2":92.0,"averageHR":50.0,"lowestSPO2":86},"averageRespiration":16.0,"lowestRespiration":12.0,"highestRespiration":22.0,"retro":false},{"sleepStartTimestampGMT":"2021-09-09T04:24:00.0","sleepEndTimestampGMT":"2021-09-09T12:46:00.0","calendarDate":"2021-09-09","sleepWindowConfirmationType":"ENHANCED_CONFIRMED_FINAL","deepSleepSeconds":4320,"lightSleepSeconds":19080,"remSleepSeconds":6240,"awakeSleepSeconds":480,"unmeasurableSeconds":0,"spo2SleepSummary":{"userProfilePk":1520967,"deviceId":3359304790,"sleepMeasurementStartGMT":"2021-09-09T04:25:00.0","sleepMeasurementEndGMT":"2021-09-09T11:25:00.0","averageSPO2":93.0,"averageHR":47.0,"lowestSPO2":88},"averageRespiration":15.0,"lowestRespiration":11.0,"highestRespiration":21.0,"retro":false,"awakeCount":1,"avgSleepStress":6.734020618556701,"sleepScores":{"overallScore":95,"qualityScore":92,"durationScore":100,"recoveryScore":100,"deepScore":77,"remScore":84,"lightScore":76,"awakeningsCountScore":87,"awakeTimeScore":96,"combinedAwakeScore":91,"restfulnessScore":75,"feedback":"POSITIVE_HIGHLY_RECOVERING","insight":"POSITIVE_ACCLIMATIZATION_IN_PROGRESS"}},{"sleepStartTimestampGMT":"2021-09-10T03:49:00.0","sleepEndTimestampGMT":"2021-09-10T12:44:00.0","calendarDate":"2021-09-10","sleepWindowConfirmationType":"ENHANCED_CONFIRMED_FINAL","deepSleepSeconds":1260,"lightSleepSeconds":24360,"remSleepSeconds":5340,"awakeSleepSeconds":1140,"unmeasurableSeconds":0,"spo2SleepSummary":{"userProfilePk":1520967,"deviceId":3359304790,"sleepMeasurementStartGMT":"2021-09-10T03:50:00.0","sleepMeasurementEndGMT":"2021-09-10T11:25:00.0","averageSPO2":94.0,"averageHR":51.0,"lowestSPO2":89},"averageRespiration":15.0,"lowestRespiration":8.0,"highestRespiration":21.0,"retro":false,"awakeCount":2,"avgSleepStress":13.623595505617978,"sleepScores":{"overallScore":80,"qualityScore":72,"durationScore":100,"recoveryScore":86,"deepScore":0,"remScore":69,"lightScore":11,"awakeningsCountScore":75,"awakeTimeScore":81,"combinedAwakeScore":78,"restfulnessScore":65,"feedback":"POSITIVE_LONG_AND_RECOVERING","insight":"POSITIVE_ACCLIMATIZATION_IN_PROGRESS"}},{"sleepStartTimestampGMT":"2021-09-11T04:06:00.0","sleepEndTimestampGMT":"2021-09-11T12:15:00.0","calendarDate":"2021-09-11","sleepWindowConfirmationType":"ENHANCED_CONFIRMED_FINAL","deepSleepSeconds":2160,"lightSleepSeconds":21600,"remSleepSeconds":4380,"awakeSleepSeconds":1200,"unmeasurableSeconds":0,"spo2SleepSummary":{"userProfilePk":1520967,"deviceId":3359304790,"sleepMeasurementStartGMT":"2021-09-11T04:07:00.0","sleepMeasurementEndGMT":"2021-09-11T11:25:00.0","averageSPO2":94.0,"averageHR":54.0,"lowestSPO2":90},"averageRespiration":14.0,"lowestRespiration":9.0,"highestRespiration":21.0,"retro":false,"awakeCount":1,"avgSleepStress":9.860655737704919,"sleepScores":{"overallScore":88,"qualityScore":84,"durationScore":97,"recoveryScore":99,"deepScore":36,"remScore":64,"lightScore":26,"awakeningsCountScore":87,"awakeTimeScore":80,"combinedAwakeScore":83,"restfulnessScore":77,"feedback":"POSITIVE_LONG_AND_RECOVERING","insight":"POSITIVE_ACCLIMATIZATION_IN_PROGRESS"}},{"sleepStartTimestampGMT":"2021-09-12T03:50:00.0","sleepEndTimestampGMT":"2021-09-12T13:06:00.0","calendarDate":"2021-09-12","sleepWindowConfirmationType":"ENHANCED_CONFIRMED_FINAL","deepSleepSeconds":4320,"lightSleepSeconds":18840,"remSleepSeconds":9960,"awakeSleepSeconds":240,"unmeasurableSeconds":0,"spo2SleepSummary":{"userProfilePk":1520967,"deviceId":3359304790,"sleepMeasurementStartGMT":"2021-09-12T03:52:00.0","sleepMeasurementEndGMT":"2021-09-12T11:25:00.0","averageSPO2":92.0,"averageHR":48.0,"lowestSPO2":87},"averageRespiration":14.0,"lowestRespiration":8.0,"highestRespiration":20.0,"retro":false,"awakeCount":0,"avgSleepStress":6.831826401446655,"sleepScores":{"overallScore":95,"qualityScore":93,"durationScore":100,"recoveryScore":100,"deepScore":72,"remScore":83,"lightScore":97,"awakeningsCountScore":100,"awakeTimeScore":100,"combinedAwakeScore":100,"restfulnessScore":75,"feedback":"POSITIVE_HIGHLY_RECOVERING","insight":"POSITIVE_EXERCISE"}},{"sleepStartTimestampGMT":"2021-09-13T04:14:00.0","sleepEndTimestampGMT":"2021-09-13T12:48:00.0","calendarDate":"2021-09-13","sleepWindowConfirmationType":"ENHANCED_CONFIRMED_FINAL","deepSleepSeconds":2520,"lightSleepSeconds":18720,"remSleepSeconds":8160,"awakeSleepSeconds":1440,"unmeasurableSeconds":0,"spo2SleepSummary":{"userProfilePk":1520967,"deviceId":3359304790,"sleepMeasurementStartGMT":"2021-09-13T04:15:00.0","sleepMeasurementEndGMT":"2021-09-13T11:24:00.0","averageSPO2":93.0,"averageHR":48.0,"lowestSPO2":87},"averageRespiration":14.0,"lowestRespiration":9.0,"highestRespiration":20.0,"retro":false,"awakeCount":2,"avgSleepStress":9.53112840466926,"sleepScores":{"overallScore":89,"qualityScore":83,"durationScore":100,"recoveryScore":100,"deepScore":48,"remScore":98,"lightScore":78,"awakeningsCountScore":75,"awakeTimeScore":76,"combinedAwakeScore":75,"restfulnessScore":37,"feedback":"POSITIVE_LONG_AND_RECOVERING","insight":"NONE"}},{"sleepStartTimestampGMT":"2021-09-14T03:47:00.0","sleepEndTimestampGMT":"2021-09-14T12:44:00.0","calendarDate":"2021-09-14","sleepWindowConfirmationType":"ENHANCED_CONFIRMED_FINAL","deepSleepSeconds":360,"lightSleepSeconds":22260,"remSleepSeconds":8940,"awakeSleepSeconds":660,"unmeasurableSeconds":0,"spo2SleepSummary":{"userProfilePk":1520967,"deviceId":3359304790,"sleepMeasurementStartGMT":"2021-09-14T03:48:00.0","sleepMeasurementEndGMT":"2021-09-14T11:25:00.0","averageSPO2":92.0,"averageHR":49.0,"lowestSPO2":85},"averageRespiration":15.0,"lowestRespiration":9.0,"highestRespiration":21.0,"retro":false,"awakeCount":1,"avgSleepStress":9.7243947858473,"sleepScores":{"overallScore":89,"qualityScore":83,"durationScore":100,"recoveryScore":98,"deepScore":0,"remScore":94,"lightScore":64,"awakeningsCountScore":87,"awakeTimeScore":92,"combinedAwakeScore":89,"restfulnessScore":67,"feedback":"POSITIVE_LONG_AND_RECOVERING","insight":"NONE"}},{"sleepStartTimestampGMT":"2021-09-15T02:44:00.0","sleepEndTimestampGMT":"2021-09-15T12:39:00.0","calendarDate":"2021-09-15","sleepWindowConfirmationType":"ENHANCED_CONFIRMED_FINAL","deepSleepSeconds":3180,"lightSleepSeconds":21780,"remSleepSeconds":8580,"awakeSleepSeconds":2160,"unmeasurableSeconds":0,"spo2SleepSummary":{"userProfilePk":1520967,"deviceId":3359304790,"sleepMeasurementStartGMT":"2021-09-15T02:45:00.0","sleepMeasurementEndGMT":"2021-09-15T11:25:00.0","averageSPO2":94.0,"averageHR":49.0,"lowestSPO2":87},"averageRespiration":15.0,"lowestRespiration":9.0,"highestRespiration":21.0,"retro":false,"awakeCount":2,"avgSleepStress":9.092150170648464,"sleepScores":{"overallScore":92,"qualityScore":88,"durationScore":100,"recoveryScore":100,"deepScore":60,"remScore":100,"lightScore":75,"awakeningsCountScore":75,"awakeTimeScore":64,"combinedAwakeScore":69,"restfulnessScore":76,"feedback":"POSITIVE_LONG_AND_RECOVERING","insight":"NONE"}},{"sleepStartTimestampGMT":"2021-09-16T03:35:00.0","sleepEndTimestampGMT":"2021-09-16T12:38:00.0","calendarDate":"2021-09-16","sleepWindowConfirmationType":"ENHANCED_CONFIRMED_FINAL","deepSleepSeconds":840,"lightSleepSeconds":22200,"remSleepSeconds":7860,"awakeSleepSeconds":1680,"unmeasurableSeconds":0,"spo2SleepSummary":{"userProfilePk":1520967,"deviceId":3359304790,"sleepMeasurementStartGMT":"2021-09-16T03:36:00.0","sleepMeasurementEndGMT":"2021-09-16T11:25:00.0","averageSPO2":92.0,"averageHR":54.0,"lowestSPO2":86},"averageRespiration":16.0,"lowestRespiration":11.0,"highestRespiration":22.0,"retro":false,"awakeCount":2,"avgSleepStress":16.550644567219152,"sleepScores":{"overallScore":79,"qualityScore":70,"durationScore":100,"recoveryScore":76,"deepScore":0,"remScore":100,"lightScore":61,"awakeningsCountScore":75,"awakeTimeScore":72,"combinedAwakeScore":73,"restfulnessScore":69,"feedback":"POSITIVE_LONG_AND_REFRESHING","insight":"NONE"}},{"sleepStartTimestampGMT":"2021-09-17T03:36:00.0","sleepEndTimestampGMT":"2021-09-17T12:34:00.0","calendarDate":"2021-09-17","sleepWindowConfirmationType":"ENHANCED_CONFIRMED_FINAL","deepSleepSeconds":2580,"lightSleepSeconds":22680,"remSleepSeconds":5580,"awakeSleepSeconds":1440,"unmeasurableSeconds":0,"spo2SleepSummary":{"userProfilePk":1520967,"deviceId":3359304790,"sleepMeasurementStartGMT":"2021-09-17T03:37:00.0","sleepMeasurementEndGMT":"2021-09-17T11:24:00.0","averageSPO2":93.0,"averageHR":55.0,"lowestSPO2":88},"averageRespiration":14.0,"lowestRespiration":9.0,"highestRespiration":22.0,"retro":false,"awakeCount":3,"avgSleepStress":13.899253731343284,"sleepScores":{"overallScore":83,"qualityScore":75,"durationScore":100,"recoveryScore":84,"deepScore":45,"remScore":72,"lightScore":52,"awakeningsCountScore":65,"awakeTimeScore":76,"combinedAwakeScore":70,"restfulnessScore":72,"feedback":"POSITIVE_LONG_AND_RECOVERING","insight":"NONE"}},{"sleepStartTimestampGMT":"2021-09-18T04:29:00.0","sleepEndTimestampGMT":"2021-09-18T13:39:00.0","calendarDate":"2021-09-18","sleepWindowConfirmationType":"ENHANCED_CONFIRMED_FINAL","deepSleepSeconds":1260,"lightSleepSeconds":21240,"remSleepSeconds":10500,"awakeSleepSeconds":0,"unmeasurableSeconds":0,"spo2SleepSummary":{"userProfilePk":1520967,"deviceId":3359304790,"sleepMeasurementStartGMT":"2021-09-18T04:30:00.0","sleepMeasurementEndGMT":"2021-09-18T11:25:00.0","averageSPO2":92.0,"averageHR":50.0,"lowestSPO2":86},"averageRespiration":15.0,"lowestRespiration":11.0,"highestRespiration":20.0,"retro":false,"awakeCount":0,"avgSleepStress":9.669691470054447,"sleepScores":{"overallScore":90,"qualityScore":85,"durationScore":100,"recoveryScore":99,"deepScore":0,"remScore":76,"lightScore":76,"awakeningsCountScore":100,"awakeTimeScore":100,"combinedAwakeScore":100,"restfulnessScore":77,"feedback":"POSITIVE_LONG_AND_RECOVERING","insight":"NONE"}},{"sleepStartTimestampGMT":"2021-09-19T03:39:00.0","sleepEndTimestampGMT":"2021-09-19T13:54:00.0","calendarDate":"2021-09-19","sleepWindowConfirmationType":"ENHANCED_CONFIRMED_FINAL","deepSleepSeconds":4200,"lightSleepSeconds":23520,"remSleepSeconds":8880,"awakeSleepSeconds":300,"unmeasurableSeconds":0,"spo2SleepSummary":{"userProfilePk":1520967,"deviceId":3359304790,"sleepMeasurementStartGMT":"2021-09-19T03:41:00.0","sleepMeasurementEndGMT":"2021-09-19T11:25:00.0","averageSPO2":93.0,"averageHR":50.0,"lowestSPO2":87},"averageRespiration":15.0,"lowestRespiration":12.0,"highestRespiration":21.0,"retro":false,"awakeCount":0,"avgSleepStress":11.33821138211382,"sleepScores":{"overallScore":93,"qualityScore":90,"durationScore":100,"recoveryScore":93,"deepScore":67,"remScore":100,"lightScore":76,"awakeningsCountScore":100,"awakeTimeScore":100,"combinedAwakeScore":100,"restfulnessScore":71,"feedback":"POSITIVE_OPTIMAL_STRUCTURE","insight":"NONE"}},{"sleepStartTimestampGMT":"2021-09-20T04:09:00.0","sleepEndTimestampGMT":"2021-09-20T12:44:00.0","calendarDate":"2021-09-20","sleepWindowConfirmationType":"ENHANCED_CONFIRMED_FINAL","deepSleepSeconds":2880,"lightSleepSeconds":19260,"remSleepSeconds":6420,"awakeSleepSeconds":2340,"unmeasurableSeconds":0,"spo2SleepSummary":{"userProfilePk":1520967,"deviceId":3359304790,"sleepMeasurementStartGMT":"2021-09-20T04:11:00.0","sleepMeasurementEndGMT":"2021-09-20T11:24:00.0","averageSPO2":93.0,"averageHR":53.0,"lowestSPO2":80},"averageRespiration":15.0,"lowestRespiration":9.0,"highestRespiration":21.0,"retro":false,"awakeCount":3,"avgSleepStress":12.998062015503876,"sleepScores":{"overallScore":86,"qualityScore":79,"durationScore":100,"recoveryScore":88,"deepScore":62,"remScore":93,"lightScore":70,"awakeningsCountScore":65,"awakeTimeScore":61,"combinedAwakeScore":63,"restfulnessScore":66,"feedback":"POSITIVE_LONG_AND_REFRESHING","insight":"POSITIVE_ACCLIMATIZATION_IN_PROGRESS"}},{"sleepStartTimestampGMT":"2021-09-21T04:36:00.0","sleepEndTimestampGMT":"2021-09-21T12:47:00.0","calendarDate":"2021-09-21","sleepWindowConfirmationType":"ENHANCED_CONFIRMED_FINAL","deepSleepSeconds":4380,"lightSleepSeconds":18540,"remSleepSeconds":5700,"awakeSleepSeconds":840,"unmeasurableSeconds":0,"spo2SleepSummary":{"userProfilePk":1520967,"deviceId":3359304790,"sleepMeasurementStartGMT":"2021-09-21T04:37:00.0","sleepMeasurementEndGMT":"2021-09-21T11:24:00.0","averageSPO2":94.0,"averageHR":50.0,"lowestSPO2":86},"averageRespiration":16.0,"lowestRespiration":10.0,"highestRespiration":23.0,"retro":false,"awakeCount":2,"avgSleepStress":8.635437881873727,"sleepScores":{"overallScore":93,"qualityScore":90,"durationScore":100,"recoveryScore":100,"deepScore":79,"remScore":78,"lightScore":75,"awakeningsCountScore":75,"awakeTimeScore":88,"combinedAwakeScore":81,"restfulnessScore":82,"feedback":"POSITIVE_HIGHLY_RECOVERING","insight":"POSITIVE_ACCLIMATIZATION_IN_PROGRESS"}},{"sleepStartTimestampGMT":"2021-09-22T04:35:00.0","sleepEndTimestampGMT":"2021-09-22T12:25:00.0","calendarDate":"2021-09-22","sleepWindowConfirmationType":"ENHANCED_CONFIRMED_FINAL","deepSleepSeconds":4260,"lightSleepSeconds":17460,"remSleepSeconds":5340,"awakeSleepSeconds":1140,"unmeasurableSeconds":0,"spo2SleepSummary":{"userProfilePk":1520967,"deviceId":3359304790,"sleepMeasurementStartGMT":"2021-09-22T04:36:00.0","sleepMeasurementEndGMT":"2021-09-22T11:24:00.0","averageSPO2":94.0,"averageHR":49.0,"lowestSPO2":90},"averageRespiration":16.0,"lowestRespiration":12.0,"highestRespiration":23.0,"retro":false,"awakeCount":2,"avgSleepStress":9.893842887473461,"sleepScores":{"overallScore":89,"qualityScore":89,"durationScore":90,"recoveryScore":99,"deepScore":81,"remScore":77,"lightScore":76,"awakeningsCountScore":75,"awakeTimeScore":80,"combinedAwakeScore":77,"restfulnessScore":82,"feedback":"POSITIVE_LONG_AND_RECOVERING","insight":"POSITIVE_ACCLIMATIZATION_IN_PROGRESS"}},{"sleepStartTimestampGMT":"2021-09-23T03:18:00.0","sleepEndTimestampGMT":"2021-09-23T12:51:00.0","calendarDate":"2021-09-23","sleepWindowConfirmationType":"ENHANCED_CONFIRMED_FINAL","deepSleepSeconds":1920,"lightSleepSeconds":24600,"remSleepSeconds":7860,"awakeSleepSeconds":0,"unmeasurableSeconds":0,"spo2SleepSummary":{"userProfilePk":1520967,"deviceId":3359304790,"sleepMeasurementStartGMT":"2021-09-23T03:19:00.0","sleepMeasurementEndGMT":"2021-09-23T11:25:00.0","averageSPO2":92.0,"averageHR":54.0,"lowestSPO2":86},"averageRespiration":16.0,"lowestRespiration":11.0,"highestRespiration":21.0,"retro":false,"awakeCount":0,"avgSleepStress":14.914634146341463,"sleepScores":{"overallScore":83,"qualityScore":76,"durationScore":100,"recoveryScore":79,"deepScore":8,"remScore":96,"lightScore":62,"awakeningsCountScore":100,"awakeTimeScore":100,"combinedAwakeScore":100,"restfulnessScore":59,"feedback":"NEGATIVE_LONG_BUT_LIGHT","insight":"NEGATIVE_ACCLIMATIZATION_IN_PROGRESS"}},{"sleepStartTimestampGMT":"2021-09-24T04:24:00.0","sleepEndTimestampGMT":"2021-09-24T12:44:00.0","calendarDate":"2021-09-24","sleepWindowConfirmationType":"ENHANCED_CONFIRMED_FINAL","deepSleepSeconds":4200,"lightSleepSeconds":18840,"remSleepSeconds":6420,"awakeSleepSeconds":540,"unmeasurableSeconds":0,"spo2SleepSummary":{"userProfilePk":1520967,"deviceId":3359304790,"sleepMeasurementStartGMT":"2021-09-24T04:25:00.0","sleepMeasurementEndGMT":"2021-09-24T11:10:00.0","averageSPO2":92.0,"averageHR":51.0,"lowestSPO2":83},"averageRespiration":14.0,"lowestRespiration":9.0,"highestRespiration":24.0,"retro":false,"awakeCount":1,"avgSleepStress":9.632530120481928,"sleepScores":{"overallScore":95,"qualityScore":92,"durationScore":100,"recoveryScore":99,"deepScore":76,"remScore":89,"lightScore":77,"awakeningsCountScore":87,"awakeTimeScore":95,"combinedAwakeScore":91,"restfulnessScore":79,"feedback":"POSITIVE_HIGHLY_RECOVERING","insight":"POSITIVE_ACCLIMATIZATION_IN_PROGRESS"}},{"sleepStartTimestampGMT":"2021-09-25T04:40:00.0","sleepEndTimestampGMT":"2021-09-25T13:59:00.0","calendarDate":"2021-09-25","sleepWindowConfirmationType":"ENHANCED_CONFIRMED_FINAL","deepSleepSeconds":840,"lightSleepSeconds":24720,"remSleepSeconds":5640,"awakeSleepSeconds":2340,"unmeasurableSeconds":0,"spo2SleepSummary":{"userProfilePk":1520967,"deviceId":3359304790,"sleepMeasurementStartGMT":"2021-09-25T04:41:00.0","sleepMeasurementEndGMT":"2021-09-25T11:25:00.0","averageSPO2":93.0,"averageHR":60.0,"lowestSPO2":88},"averageRespiration":15.0,"lowestRespiration":11.0,"highestRespiration":23.0,"retro":false,"awakeCount":3,"avgSleepStress":23.57039711191336,"sleepScores":{"overallScore":70,"qualityScore":58,"durationScore":100,"recoveryScore":61,"deepScore":0,"remScore":72,"lightScore":6,"awakeningsCountScore":65,"awakeTimeScore":61,"combinedAwakeScore":63,"restfulnessScore":74,"feedback":"NEGATIVE_LONG_BUT_POOR_QUALITY","insight":"NEGATIVE_ACCLIMATIZATION_IN_PROGRESS"}},{"sleepStartTimestampGMT":"2021-09-26T04:35:00.0","sleepEndTimestampGMT":"2021-09-26T13:03:00.0","calendarDate":"2021-09-26","sleepWindowConfirmationType":"ENHANCED_CONFIRMED_FINAL","deepSleepSeconds":1920,"lightSleepSeconds":22500,"remSleepSeconds":6060,"awakeSleepSeconds":0,"unmeasurableSeconds":0,"spo2SleepSummary":{"userProfilePk":1520967,"deviceId":3359304790,"sleepMeasurementStartGMT":"2021-09-26T04:36:00.0","sleepMeasurementEndGMT":"2021-09-26T11:25:00.0","averageSPO2":94.0,"averageHR":52.0,"lowestSPO2":87},"averageRespiration":15.0,"lowestRespiration":9.0,"highestRespiration":21.0,"retro":false,"awakeCount":0,"avgSleepStress":11.049212598425196,"sleepScores":{"overallScore":87,"qualityScore":81,"durationScore":100,"recoveryScore":91,"deepScore":17,"remScore":78,"lightScore":49,"awakeningsCountScore":100,"awakeTimeScore":100,"combinedAwakeScore":100,"restfulnessScore":61,"feedback":"POSITIVE_LONG_AND_CONTINUOUS","insight":"POSITIVE_ACCLIMATIZATION_IN_PROGRESS"}},{"sleepStartTimestampGMT":"2021-09-27T04:19:00.0","sleepEndTimestampGMT":"2021-09-27T12:37:00.0","calendarDate":"2021-09-27","sleepWindowConfirmationType":"ENHANCED_CONFIRMED_FINAL","deepSleepSeconds":1200,"lightSleepSeconds":22260,"remSleepSeconds":6420,"awakeSleepSeconds":0,"unmeasurableSeconds":0,"spo2SleepSummary":{"userProfilePk":1520967,"deviceId":3359304790,"sleepMeasurementStartGMT":"2021-09-27T04:20:00.0","sleepMeasurementEndGMT":"2021-09-27T11:25:00.0","averageSPO2":93.0,"averageHR":52.0,"lowestSPO2":88},"averageRespiration":14.0,"lowestRespiration":11.0,"highestRespiration":20.0,"retro":false,"awakeCount":0,"avgSleepStress":12.7374749498998,"sleepScores":{"overallScore":87,"qualityScore":80,"durationScore":100,"recoveryScore":87,"deepScore":0,"remScore":87,"lightScore":44,"awakeningsCountScore":100,"awakeTimeScore":100,"combinedAwakeScore":100,"restfulnessScore":73,"feedback":"POSITIVE_LONG_AND_CONTINUOUS","insight":"POSITIVE_ACCLIMATIZATION_IN_PROGRESS"}},{"sleepStartTimestampGMT":"2021-09-28T03:49:00.0","sleepEndTimestampGMT":"2021-09-28T12:54:00.0","calendarDate":"2021-09-28","sleepWindowConfirmationType":"ENHANCED_CONFIRMED_FINAL","deepSleepSeconds":4200,"lightSleepSeconds":19800,"remSleepSeconds":7320,"awakeSleepSeconds":1380,"unmeasurableSeconds":0,"spo2SleepSummary":{"userProfilePk":1520967,"deviceId":3359304790,"sleepMeasurementStartGMT":"2021-09-28T03:50:00.0","sleepMeasurementEndGMT":"2021-09-28T11:19:00.0","averageSPO2":92.0,"averageHR":50.0,"lowestSPO2":84},"averageRespiration":16.0,"lowestRespiration":10.0,"highestRespiration":23.0,"retro":false,"awakeCount":2,"avgSleepStress":8.566420664206642,"sleepScores":{"overallScore":91,"qualityScore":87,"durationScore":100,"recoveryScore":100,"deepScore":73,"remScore":99,"lightScore":79,"awakeningsCountScore":75,"awakeTimeScore":77,"combinedAwakeScore":76,"restfulnessScore":46,"feedback":"POSITIVE_LONG_AND_RECOVERING","insight":"POSITIVE_ACCLIMATIZATION_IN_PROGRESS"}},{"sleepStartTimestampGMT":"2021-09-29T03:39:00.0","sleepEndTimestampGMT":"2021-09-29T12:56:00.0","calendarDate":"2021-09-29","sleepWindowConfirmationType":"ENHANCED_CONFIRMED_FINAL","deepSleepSeconds":3060,"lightSleepSeconds":19080,"remSleepSeconds":8820,"awakeSleepSeconds":2460,"unmeasurableSeconds":0,"spo2SleepSummary":{"userProfilePk":1520967,"deviceId":3359304790,"sleepMeasurementStartGMT":"2021-09-29T03:40:00.0","sleepMeasurementEndGMT":"2021-09-29T11:25:00.0","averageSPO2":92.0,"averageHR":49.0,"lowestSPO2":85},"averageRespiration":15.0,"lowestRespiration":8.0,"highestRespiration":22.0,"retro":false,"awakeCount":3,"avgSleepStress":8.492779783393502,"sleepScores":{"overallScore":89,"qualityScore":84,"durationScore":100,"recoveryScore":100,"deepScore":61,"remScore":93,"lightScore":83,"awakeningsCountScore":65,"awakeTimeScore":59,"combinedAwakeScore":62,"restfulnessScore":62,"feedback":"POSITIVE_LONG_AND_RECOVERING","insight":"POSITIVE_ACCLIMATIZATION_IN_PROGRESS"}},{"sleepStartTimestampGMT":"2021-09-30T04:13:00.0","sleepEndTimestampGMT":"2021-09-30T12:53:00.0","calendarDate":"2021-09-30","sleepWindowConfirmationType":"ENHANCED_CONFIRMED_FINAL","deepSleepSeconds":4440,"lightSleepSeconds":21240,"remSleepSeconds":4320,"awakeSleepSeconds":1200,"unmeasurableSeconds":0,"spo2SleepSummary":{"userProfilePk":1520967,"deviceId":3359304790,"sleepMeasurementStartGMT":"2021-09-30T04:14:00.0","sleepMeasurementEndGMT":"2021-09-30T11:25:00.0","averageSPO2":93.0,"averageHR":49.0,"lowestSPO2":88},"averageRespiration":15.0,"lowestRespiration":11.0,"highestRespiration":22.0,"retro":false,"awakeCount":2,"avgSleepStress":9.936538461538461,"sleepScores":{"overallScore":90,"qualityScore":85,"durationScore":100,"recoveryScore":98,"deepScore":78,"remScore":59,"lightScore":63,"awakeningsCountScore":75,"awakeTimeScore":80,"combinedAwakeScore":77,"restfulnessScore":66,"feedback":"POSITIVE_LONG_AND_RECOVERING","insight":"POSITIVE_ACCLIMATIZATION_IN_PROGRESS"}},{"sleepStartTimestampGMT":"2021-10-01T03:19:00.0","sleepEndTimestampGMT":"2021-10-01T12:15:00.0","calendarDate":"2021-10-01","sleepWindowConfirmationType":"ENHANCED_CONFIRMED_FINAL","deepSleepSeconds":2340,"lightSleepSeconds":19980,"remSleepSeconds":8040,"awakeSleepSeconds":1800,"unmeasurableSeconds":0,"spo2SleepSummary":{"userProfilePk":1520967,"deviceId":3359304790,"sleepMeasurementStartGMT":"2021-10-01T03:21:00.0","sleepMeasurementEndGMT":"2021-10-01T12:15:00.0","averageSPO2":91.0,"averageHR":48.0,"lowestSPO2":83},"averageRespiration":15.0,"lowestRespiration":9.0,"highestRespiration":22.0,"retro":false,"awakeCount":3,"avgSleepStress":8.80410447761194,"sleepScores":{"overallScore":90,"qualityScore":85,"durationScore":100,"recoveryScore":100,"deepScore":36,"remScore":100,"lightScore":73,"awakeningsCountScore":65,"awakeTimeScore":70,"combinedAwakeScore":67,"restfulnessScore":76,"feedback":"POSITIVE_LONG_AND_RECOVERING","insight":"POSITIVE_ACCLIMATIZATION_IN_PROGRESS"}},{"sleepStartTimestampGMT":"2021-10-02T04:06:00.0","sleepEndTimestampGMT":"2021-10-02T12:50:00.0","calendarDate":"2021-10-02","sleepWindowConfirmationType":"ENHANCED_CONFIRMED_FINAL","deepSleepSeconds":780,"lightSleepSeconds":25080,"remSleepSeconds":4860,"awakeSleepSeconds":720,"unmeasurableSeconds":0,"spo2SleepSummary":{"userProfilePk":1520967,"deviceId":3359304790,"sleepMeasurementStartGMT":"2021-10-02T04:07:00.0","sleepMeasurementEndGMT":"2021-10-02T12:31:00.0","averageSPO2":93.0,"averageHR":51.0,"lowestSPO2":86},"averageRespiration":16.0,"lowestRespiration":11.0,"highestRespiration":21.0,"retro":false,"awakeCount":1,"avgSleepStress":12.862332695984703,"sleepScores":{"overallScore":83,"qualityScore":75,"durationScore":100,"recoveryScore":88,"deepScore":0,"remScore":64,"lightScore":0,"awakeningsCountScore":87,"awakeTimeScore":91,"combinedAwakeScore":89,"restfulnessScore":66,"feedback":"NEGATIVE_LONG_BUT_LIGHT","insight":"NEGATIVE_LATE_STRENUOUS_EXERCISE"}},{"sleepStartTimestampGMT":"2021-10-03T04:57:00.0","sleepEndTimestampGMT":"2021-10-03T12:49:00.0","calendarDate":"2021-10-03","sleepWindowConfirmationType":"ENHANCED_CONFIRMED_FINAL","deepSleepSeconds":1080,"lightSleepSeconds":20040,"remSleepSeconds":6120,"awakeSleepSeconds":1080,"unmeasurableSeconds":0,"spo2SleepSummary":{"userProfilePk":1520967,"deviceId":3359304790,"sleepMeasurementStartGMT":"2021-10-03T04:58:00.0","sleepMeasurementEndGMT":"2021-10-03T12:31:00.0","averageSPO2":92.0,"averageHR":56.0,"lowestSPO2":87},"averageRespiration":16.0,"lowestRespiration":10.0,"highestRespiration":24.0,"retro":false,"awakeCount":2,"avgSleepStress":16.42494714587738,"sleepScores":{"overallScore":77,"qualityScore":71,"durationScore":90,"recoveryScore":77,"deepScore":0,"remScore":93,"lightScore":51,"awakeningsCountScore":75,"awakeTimeScore":83,"combinedAwakeScore":79,"restfulnessScore":75,"feedback":"POSITIVE_LONG_AND_REFRESHING","insight":"POSITIVE_ACCLIMATIZATION_IN_PROGRESS"}},{"sleepStartTimestampGMT":"2021-10-04T03:54:00.0","sleepEndTimestampGMT":"2021-10-04T12:29:00.0","calendarDate":"2021-10-04","sleepWindowConfirmationType":"ENHANCED_CONFIRMED_FINAL","deepSleepSeconds":1860,"lightSleepSeconds":20040,"remSleepSeconds":7860,"awakeSleepSeconds":1140,"unmeasurableSeconds":0,"spo2SleepSummary":{"userProfilePk":1520967,"deviceId":3359304790,"sleepMeasurementStartGMT":"2021-10-04T03:55:00.0","sleepMeasurementEndGMT":"2021-10-04T12:29:00.0","averageSPO2":93.0,"averageHR":58.0,"lowestSPO2":86},"averageRespiration":15.0,"lowestRespiration":9.0,"highestRespiration":22.0,"retro":false,"awakeCount":2,"avgSleepStress":19.06019417475728,"sleepScores":{"overallScore":78,"qualityScore":69,"durationScore":100,"recoveryScore":70,"deepScore":17,"remScore":100,"lightScore":70,"awakeningsCountScore":75,"awakeTimeScore":81,"combinedAwakeScore":78,"restfulnessScore":68,"feedback":"POSITIVE_LONG_AND_REFRESHING","insight":"POSITIVE_ACCLIMATIZATION_IN_PROGRESS"}},{"sleepStartTimestampGMT":"2021-10-05T03:13:00.0","sleepEndTimestampGMT":"2021-10-05T11:18:00.0","calendarDate":"2021-10-05","sleepWindowConfirmationType":"ENHANCED_CONFIRMED_FINAL","deepSleepSeconds":660,"lightSleepSeconds":14580,"remSleepSeconds":6060,"awakeSleepSeconds":7800,"unmeasurableSeconds":0,"spo2SleepSummary":{"userProfilePk":1520967,"deviceId":3359304790,"sleepMeasurementStartGMT":"2021-10-05T03:14:00.0","sleepMeasurementEndGMT":"2021-10-05T11:18:00.0","averageSPO2":91.0,"averageHR":75.0,"lowestSPO2":86},"averageRespiration":14.0,"lowestRespiration":9.0,"highestRespiration":27.0,"retro":false,"awakeCount":1,"avgSleepStress":58.02880658436214,"sleepScores":{"overallScore":12,"qualityScore":13,"durationScore":63,"recoveryScore":0,"deepScore":0,"remScore":85,"lightScore":71,"awakeningsCountScore":75,"awakeTimeScore":0,"combinedAwakeScore":37,"restfulnessScore":100,"feedback":"NEGATIVE_POOR_STRUCTURE","insight":"NEGATIVE_ACCLIMATIZATION_IN_PROGRESS"}},{"sleepStartTimestampGMT":"2021-10-06T01:51:00.0","sleepEndTimestampGMT":"2021-10-06T12:33:00.0","calendarDate":"2021-10-06","sleepWindowConfirmationType":"ENHANCED_CONFIRMED_FINAL","deepSleepSeconds":4920,"lightSleepSeconds":23580,"remSleepSeconds":9240,"awakeSleepSeconds":780,"unmeasurableSeconds":0,"spo2SleepSummary":{"userProfilePk":1520967,"deviceId":3359304790,"sleepMeasurementStartGMT":"2021-10-06T03:01:00.0","sleepMeasurementEndGMT":"2021-10-06T12:30:00.0","averageSPO2":93.0,"averageHR":54.0,"lowestSPO2":85},"averageRespiration":15.0,"lowestRespiration":8.0,"highestRespiration":25.0,"retro":false,"awakeCount":1,"avgSleepStress":11.307692307692308,"sleepScores":{"overallScore":90,"qualityScore":85,"durationScore":100,"recoveryScore":88,"deepScore":72,"remScore":100,"lightScore":80,"awakeningsCountScore":87,"awakeTimeScore":89,"combinedAwakeScore":88,"restfulnessScore":65,"feedback":"POSITIVE_LONG_AND_REFRESHING","insight":"POSITIVE_ACCLIMATIZATION_IN_PROGRESS"}},{"sleepStartTimestampGMT":"2021-10-07T04:31:00.0","sleepEndTimestampGMT":"2021-10-07T12:45:00.0","calendarDate":"2021-10-07","sleepWindowConfirmationType":"ENHANCED_CONFIRMED_FINAL","deepSleepSeconds":1380,"lightSleepSeconds":21240,"remSleepSeconds":6180,"awakeSleepSeconds":840,"unmeasurableSeconds":0,"spo2SleepSummary":{"userProfilePk":1520967,"deviceId":3359304790,"sleepMeasurementStartGMT":"2021-10-07T04:32:00.0","sleepMeasurementEndGMT":"2021-10-07T12:45:00.0","averageSPO2":94.0,"averageHR":50.0,"lowestSPO2":90},"averageRespiration":15.0,"lowestRespiration":8.0,"highestRespiration":21.0,"retro":false,"awakeCount":1,"avgSleepStress":8.697768762677486,"sleepScores":{"overallScore":91,"qualityScore":86,"durationScore":100,"recoveryScore":100,"deepScore":0,"remScore":86,"lightScore":50,"awakeningsCountScore":87,"awakeTimeScore":88,"combinedAwakeScore":87,"restfulnessScore":95,"feedback":"POSITIVE_LONG_AND_RECOVERING","insight":"POSITIVE_ACCLIMATIZATION_IN_PROGRESS"}},{"sleepStartTimestampGMT":"2021-10-08T03:26:00.0","sleepEndTimestampGMT":"2021-10-08T12:45:00.0","calendarDate":"2021-10-08","sleepWindowConfirmationType":"ENHANCED_CONFIRMED_FINAL","deepSleepSeconds":4260,"lightSleepSeconds":21540,"remSleepSeconds":7320,"awakeSleepSeconds":420,"unmeasurableSeconds":0,"spo2SleepSummary":{"userProfilePk":1520967,"deviceId":3359304790,"sleepMeasurementStartGMT":"2021-10-08T03:27:00.0","sleepMeasurementEndGMT":"2021-10-08T12:45:00.0","averageSPO2":93.0,"averageHR":48.0,"lowestSPO2":83},"averageRespiration":16.0,"lowestRespiration":9.0,"highestRespiration":22.0,"retro":false,"awakeCount":1,"avgSleepStress":9.443649373881932,"sleepScores":{"overallScore":95,"qualityScore":92,"durationScore":100,"recoveryScore":100,"deepScore":71,"remScore":91,"lightScore":75,"awakeningsCountScore":87,"awakeTimeScore":97,"combinedAwakeScore":92,"restfulnessScore":74,"feedback":"POSITIVE_HIGHLY_RECOVERING","insight":"POSITIVE_ACCLIMATIZATION_IN_PROGRESS"}},{"sleepStartTimestampGMT":"2021-10-09T03:19:00.0","sleepEndTimestampGMT":"2021-10-09T13:43:00.0","calendarDate":"2021-10-09","sleepWindowConfirmationType":"ENHANCED_CONFIRMED_FINAL","deepSleepSeconds":1680,"lightSleepSeconds":26580,"remSleepSeconds":7020,"awakeSleepSeconds":2160,"unmeasurableSeconds":0,"spo2SleepSummary":{"userProfilePk":1520967,"deviceId":3359304790,"sleepMeasurementStartGMT":"2021-10-09T03:21:00.0","sleepMeasurementEndGMT":"2021-10-09T13:32:00.0","averageSPO2":94.0,"averageHR":49.0,"lowestSPO2":85},"averageRespiration":14.0,"lowestRespiration":9.0,"highestRespiration":21.0,"retro":false,"awakeCount":2,"avgSleepStress":10.993579454253611,"sleepScores":{"overallScore":83,"qualityScore":75,"durationScore":100,"recoveryScore":94,"deepScore":0,"remScore":78,"lightScore":37,"awakeningsCountScore":75,"awakeTimeScore":64,"combinedAwakeScore":69,"restfulnessScore":62,"feedback":"NEGATIVE_LONG_BUT_LIGHT","insight":"NEGATIVE_ACCLIMATIZATION_IN_PROGRESS"}},{"sleepStartTimestampGMT":"2021-10-10T03:17:00.0","sleepEndTimestampGMT":"2021-10-10T12:15:00.0","calendarDate":"2021-10-10","sleepWindowConfirmationType":"ENHANCED_CONFIRMED_FINAL","deepSleepSeconds":4500,"lightSleepSeconds":19200,"remSleepSeconds":8220,"awakeSleepSeconds":360,"unmeasurableSeconds":0,"spo2SleepSummary":{"userProfilePk":1520967,"deviceId":3359304790,"sleepMeasurementStartGMT":"2021-10-10T03:18:00.0","sleepMeasurementEndGMT":"2021-10-10T12:15:00.0","averageSPO2":93.0,"averageHR":49.0,"lowestSPO2":81},"averageRespiration":15.0,"lowestRespiration":9.0,"highestRespiration":24.0,"retro":false,"awakeCount":1,"avgSleepStress":10.652985074626866,"sleepScores":{"overallScore":95,"qualityScore":92,"durationScore":100,"recoveryScore":95,"deepScore":75,"remScore":100,"lightScore":87,"awakeningsCountScore":87,"awakeTimeScore":99,"combinedAwakeScore":93,"restfulnessScore":82,"feedback":"POSITIVE_OPTIMAL_STRUCTURE","insight":"POSITIVE_ACCLIMATIZATION_IN_PROGRESS"}},{"sleepStartTimestampGMT":"2021-10-11T03:44:00.0","sleepEndTimestampGMT":"2021-10-11T12:28:00.0","calendarDate":"2021-10-11","sleepWindowConfirmationType":"ENHANCED_CONFIRMED_FINAL","deepSleepSeconds":2760,"lightSleepSeconds":20580,"remSleepSeconds":7620,"awakeSleepSeconds":480,"unmeasurableSeconds":0,"spo2SleepSummary":{"userProfilePk":1520967,"deviceId":3359304790,"sleepMeasurementStartGMT":"2021-10-11T04:22:00.0","sleepMeasurementEndGMT":"2021-10-11T12:28:00.0","averageSPO2":94.0,"averageHR":49.0,"lowestSPO2":86},"averageRespiration":15.0,"lowestRespiration":8.0,"highestRespiration":21.0,"retro":false,"awakeCount":1,"avgSleepStress":11.196564885496183,"sleepScores":{"overallScore":91,"qualityScore":87,"durationScore":100,"recoveryScore":92,"deepScore":52,"remScore":100,"lightScore":72,"awakeningsCountScore":87,"awakeTimeScore":96,"combinedAwakeScore":91,"restfulnessScore":76,"feedback":"POSITIVE_LONG_AND_REFRESHING","insight":"POSITIVE_ACCLIMATIZATION_IN_PROGRESS"}},{"sleepStartTimestampGMT":"2021-10-12T04:08:00.0","sleepEndTimestampGMT":"2021-10-12T12:43:00.0","calendarDate":"2021-10-12","sleepWindowConfirmationType":"ENHANCED_CONFIRMED_FINAL","deepSleepSeconds":4500,"lightSleepSeconds":20160,"remSleepSeconds":5640,"awakeSleepSeconds":600,"unmeasurableSeconds":0,"spo2SleepSummary":{"userProfilePk":1520967,"deviceId":3359304790,"sleepMeasurementStartGMT":"2021-10-12T04:09:00.0","sleepMeasurementEndGMT":"2021-10-12T12:43:00.0","averageSPO2":94.0,"averageHR":49.0,"lowestSPO2":84},"averageRespiration":14.0,"lowestRespiration":8.0,"highestRespiration":19.0,"retro":false,"awakeCount":1,"avgSleepStress":11.366279069767442,"sleepScores":{"overallScore":91,"qualityScore":87,"durationScore":100,"recoveryScore":92,"deepScore":78,"remScore":74,"lightScore":72,"awakeningsCountScore":87,"awakeTimeScore":93,"combinedAwakeScore":90,"restfulnessScore":78,"feedback":"POSITIVE_LONG_AND_RECOVERING","insight":"POSITIVE_ACCLIMATIZATION_IN_PROGRESS"}},{"sleepStartTimestampGMT":"2021-10-13T04:44:00.0","sleepEndTimestampGMT":"2021-10-13T12:42:00.0","calendarDate":"2021-10-13","sleepWindowConfirmationType":"ENHANCED_CONFIRMED_FINAL","deepSleepSeconds":3720,"lightSleepSeconds":16740,"remSleepSeconds":7440,"awakeSleepSeconds":780,"unmeasurableSeconds":0,"spo2SleepSummary":{"userProfilePk":1520967,"deviceId":3359304790,"sleepMeasurementStartGMT":"2021-10-13T04:45:00.0","sleepMeasurementEndGMT":"2021-10-13T12:42:00.0","averageSPO2":93.0,"averageHR":50.0,"lowestSPO2":83},"averageRespiration":15.0,"lowestRespiration":9.0,"highestRespiration":22.0,"retro":false,"awakeCount":1,"avgSleepStress":11.23157894736842,"sleepScores":{"overallScore":91,"qualityScore":89,"durationScore":95,"recoveryScore":93,"deepScore":73,"remScore":100,"lightScore":88,"awakeningsCountScore":87,"awakeTimeScore":89,"combinedAwakeScore":88,"restfulnessScore":74,"feedback":"POSITIVE_LONG_AND_REFRESHING","insight":"POSITIVE_ACCLIMATIZATION_IN_PROGRESS"}},{"sleepStartTimestampGMT":"2021-10-14T05:39:00.0","sleepEndTimestampGMT":"2021-10-14T12:50:00.0","calendarDate":"2021-10-14","sleepWindowConfirmationType":"ENHANCED_CONFIRMED_FINAL","deepSleepSeconds":600,"lightSleepSeconds":18960,"remSleepSeconds":4920,"awakeSleepSeconds":1380,"unmeasurableSeconds":0,"spo2SleepSummary":{"userProfilePk":1520967,"deviceId":3359304790,"sleepMeasurementStartGMT":"2021-10-14T05:40:00.0","sleepMeasurementEndGMT":"2021-10-14T12:50:00.0","averageSPO2":93.0,"averageHR":55.0,"lowestSPO2":86},"averageRespiration":15.0,"lowestRespiration":9.0,"highestRespiration":21.0,"retro":false,"awakeCount":2,"avgSleepStress":15.807058823529411,"sleepScores":{"overallScore":67,"qualityScore":62,"durationScore":76,"recoveryScore":77,"deepScore":0,"remScore":79,"lightScore":20,"awakeningsCountScore":75,"awakeTimeScore":77,"combinedAwakeScore":76,"restfulnessScore":1,"feedback":"NEGATIVE_LIGHT","insight":"NEGATIVE_ACCLIMATIZATION_IN_PROGRESS"}},{"sleepStartTimestampGMT":"2021-10-15T03:59:00.0","sleepEndTimestampGMT":"2021-10-15T12:29:00.0","calendarDate":"2021-10-15","sleepWindowConfirmationType":"ENHANCED_CONFIRMED_FINAL","deepSleepSeconds":3840,"lightSleepSeconds":20880,"remSleepSeconds":5100,"awakeSleepSeconds":780,"unmeasurableSeconds":0,"spo2SleepSummary":{"userProfilePk":1520967,"deviceId":3359304790,"sleepMeasurementStartGMT":"2021-10-15T04:00:00.0","sleepMeasurementEndGMT":"2021-10-15T12:29:00.0","averageSPO2":94.0,"averageHR":48.0,"lowestSPO2":87},"averageRespiration":16.0,"lowestRespiration":11.0,"highestRespiration":24.0,"retro":false,"awakeCount":1,"avgSleepStress":6.547244094488189,"sleepScores":{"overallScore":93,"qualityScore":90,"durationScore":100,"recoveryScore":100,"deepScore":71,"remScore":69,"lightScore":65,"awakeningsCountScore":87,"awakeTimeScore":89,"combinedAwakeScore":88,"restfulnessScore":80,"feedback":"POSITIVE_HIGHLY_RECOVERING","insight":"POSITIVE_ACCLIMATIZATION_IN_PROGRESS"}},{"sleepStartTimestampGMT":"2021-10-16T04:40:00.0","sleepEndTimestampGMT":"2021-10-16T12:30:00.0","calendarDate":"2021-10-16","sleepWindowConfirmationType":"ENHANCED_CONFIRMED_FINAL","deepSleepSeconds":3000,"lightSleepSeconds":19500,"remSleepSeconds":5700,"awakeSleepSeconds":0,"unmeasurableSeconds":0,"spo2SleepSummary":{"userProfilePk":1520967,"deviceId":3359304790,"sleepMeasurementStartGMT":"2021-10-16T04:41:00.0","sleepMeasurementEndGMT":"2021-10-16T12:30:00.0","averageSPO2":93.0,"averageHR":47.0,"lowestSPO2":88},"averageRespiration":15.0,"lowestRespiration":9.0,"highestRespiration":24.0,"retro":false,"awakeCount":0,"avgSleepStress":6.757446808510639,"sleepScores":{"overallScore":93,"qualityScore":91,"durationScore":97,"recoveryScore":100,"deepScore":64,"remScore":79,"lightScore":67,"awakeningsCountScore":100,"awakeTimeScore":100,"combinedAwakeScore":100,"restfulnessScore":70,"feedback":"POSITIVE_HIGHLY_RECOVERING","insight":"POSITIVE_ACCLIMATIZATION_IN_PROGRESS"}},{"sleepStartTimestampGMT":"2021-10-17T04:19:00.0","sleepEndTimestampGMT":"2021-10-17T13:45:00.0","calendarDate":"2021-10-17","sleepWindowConfirmationType":"ENHANCED_CONFIRMED_FINAL","deepSleepSeconds":1020,"lightSleepSeconds":25080,"remSleepSeconds":6420,"awakeSleepSeconds":1440,"unmeasurableSeconds":0,"spo2SleepSummary":{"userProfilePk":1520967,"deviceId":3359304790,"sleepMeasurementStartGMT":"2021-10-17T04:20:00.0","sleepMeasurementEndGMT":"2021-10-17T13:32:00.0","averageSPO2":93.0,"averageHR":52.0,"lowestSPO2":87},"averageRespiration":16.0,"lowestRespiration":11.0,"highestRespiration":22.0,"retro":false,"awakeCount":2,"avgSleepStress":13.456989247311828,"sleepScores":{"overallScore":80,"qualityScore":72,"durationScore":100,"recoveryScore":84,"deepScore":0,"remScore":77,"lightScore":23,"awakeningsCountScore":75,"awakeTimeScore":76,"combinedAwakeScore":75,"restfulnessScore":67,"feedback":"POSITIVE_LONG_AND_RECOVERING","insight":"POSITIVE_ACCLIMATIZATION_IN_PROGRESS"}},{"sleepStartTimestampGMT":"2021-10-18T04:14:00.0","sleepEndTimestampGMT":"2021-10-18T12:44:00.0","calendarDate":"2021-10-18","sleepWindowConfirmationType":"ENHANCED_CONFIRMED_FINAL","deepSleepSeconds":4380,"lightSleepSeconds":20940,"remSleepSeconds":4380,"awakeSleepSeconds":900,"unmeasurableSeconds":0,"spo2SleepSummary":{"userProfilePk":1520967,"deviceId":3359304790,"sleepMeasurementStartGMT":"2021-10-18T04:15:00.0","sleepMeasurementEndGMT":"2021-10-18T12:43:00.0","averageSPO2":93.0,"averageHR":48.0,"lowestSPO2":86},"averageRespiration":17.0,"lowestRespiration":11.0,"highestRespiration":24.0,"retro":false,"awakeCount":1,"avgSleepStress":4.854581673306773,"sleepScores":{"overallScore":92,"qualityScore":88,"durationScore":100,"recoveryScore":100,"deepScore":78,"remScore":61,"lightScore":64,"awakeningsCountScore":87,"awakeTimeScore":87,"combinedAwakeScore":87,"restfulnessScore":66,"feedback":"POSITIVE_LONG_AND_RECOVERING","insight":"POSITIVE_ACCLIMATIZATION_IN_PROGRESS"}},{"sleepStartTimestampGMT":"2021-10-19T04:27:00.0","sleepEndTimestampGMT":"2021-10-19T12:41:00.0","calendarDate":"2021-10-19","sleepWindowConfirmationType":"ENHANCED_CONFIRMED_FINAL","deepSleepSeconds":1860,"lightSleepSeconds":21480,"remSleepSeconds":6300,"awakeSleepSeconds":0,"unmeasurableSeconds":0,"spo2SleepSummary":{"userProfilePk":1520967,"deviceId":3359304790,"sleepMeasurementStartGMT":"2021-10-19T04:28:00.0","sleepMeasurementEndGMT":"2021-10-19T12:41:00.0","averageSPO2":93.0,"averageHR":53.0,"lowestSPO2":87},"averageRespiration":15.0,"lowestRespiration":9.0,"highestRespiration":22.0,"retro":false,"awakeCount":0,"avgSleepStress":14.52129817444219,"sleepScores":{"overallScore":85,"qualityScore":78,"durationScore":100,"recoveryScore":83,"deepScore":17,"remScore":85,"lightScore":60,"awakeningsCountScore":100,"awakeTimeScore":100,"combinedAwakeScore":100,"restfulnessScore":64,"feedback":"NEGATIVE_LONG_BUT_LIGHT","insight":"NEGATIVE_ACCLIMATIZATION_IN_PROGRESS"}},{"sleepStartTimestampGMT":"2021-10-20T04:43:00.0","sleepEndTimestampGMT":"2021-10-20T12:51:00.0","calendarDate":"2021-10-20","sleepWindowConfirmationType":"ENHANCED_CONFIRMED_FINAL","deepSleepSeconds":1560,"lightSleepSeconds":21060,"remSleepSeconds":6240,"awakeSleepSeconds":420,"unmeasurableSeconds":0,"spo2SleepSummary":{"userProfilePk":1520967,"deviceId":3359304790,"sleepMeasurementStartGMT":"2021-10-20T04:44:00.0","sleepMeasurementEndGMT":"2021-10-20T12:51:00.0","averageSPO2":93.0,"averageHR":48.0,"lowestSPO2":87},"averageRespiration":15.0,"lowestRespiration":9.0,"highestRespiration":20.0,"retro":false,"awakeCount":1,"avgSleepStress":4.622767857142857,"sleepScores":{"overallScore":89,"qualityScore":84,"durationScore":100,"recoveryScore":100,"deepScore":5,"remScore":87,"lightScore":56,"awakeningsCountScore":87,"awakeTimeScore":97,"combinedAwakeScore":92,"restfulnessScore":66,"feedback":"POSITIVE_LONG_AND_RECOVERING","insight":"POSITIVE_ACCLIMATIZATION_IN_PROGRESS"}},{"sleepStartTimestampGMT":"2021-10-21T05:11:00.0","sleepEndTimestampGMT":"2021-10-21T12:55:00.0","calendarDate":"2021-10-21","sleepWindowConfirmationType":"ENHANCED_CONFIRMED_FINAL","deepSleepSeconds":420,"lightSleepSeconds":21600,"remSleepSeconds":4920,"awakeSleepSeconds":900,"unmeasurableSeconds":0,"spo2SleepSummary":{"userProfilePk":1520967,"deviceId":3359304790,"sleepMeasurementStartGMT":"2021-10-21T05:12:00.0","sleepMeasurementEndGMT":"2021-10-21T12:55:00.0","averageSPO2":94.0,"averageHR":47.0,"lowestSPO2":89},"averageRespiration":16.0,"lowestRespiration":9.0,"highestRespiration":21.0,"retro":false,"awakeCount":2,"avgSleepStress":8.34341252699784,"sleepScores":{"overallScore":83,"qualityScore":80,"durationScore":88,"recoveryScore":100,"deepScore":0,"remScore":73,"lightScore":0,"awakeningsCountScore":75,"awakeTimeScore":87,"combinedAwakeScore":81,"restfulnessScore":64,"feedback":"POSITIVE_LONG_AND_RECOVERING","insight":"POSITIVE_ACCLIMATIZATION_IN_PROGRESS"}},{"sleepStartTimestampGMT":"2021-10-22T03:50:00.0","sleepEndTimestampGMT":"2021-10-22T12:52:00.0","calendarDate":"2021-10-22","sleepWindowConfirmationType":"ENHANCED_CONFIRMED_FINAL","deepSleepSeconds":3480,"lightSleepSeconds":22680,"remSleepSeconds":5400,"awakeSleepSeconds":960,"unmeasurableSeconds":0,"spo2SleepSummary":{"userProfilePk":1520967,"deviceId":3359304790,"sleepMeasurementStartGMT":"2021-10-22T03:51:00.0","sleepMeasurementEndGMT":"2021-10-22T12:52:00.0","averageSPO2":93.0,"averageHR":49.0,"lowestSPO2":86},"averageRespiration":16.0,"lowestRespiration":11.0,"highestRespiration":23.0,"retro":false,"awakeCount":1,"avgSleepStress":8.43807763401109,"sleepScores":{"overallScore":90,"qualityScore":85,"durationScore":100,"recoveryScore":100,"deepScore":65,"remScore":69,"lightScore":61,"awakeningsCountScore":87,"awakeTimeScore":85,"combinedAwakeScore":86,"restfulnessScore":48,"feedback":"POSITIVE_LONG_AND_RECOVERING","insight":"POSITIVE_ACCLIMATIZATION_IN_PROGRESS"}},{"sleepStartTimestampGMT":"2021-10-23T03:46:00.0","sleepEndTimestampGMT":"2021-10-23T12:52:00.0","calendarDate":"2021-10-23","sleepWindowConfirmationType":"ENHANCED_CONFIRMED_FINAL","deepSleepSeconds":1800,"lightSleepSeconds":24540,"remSleepSeconds":5100,"awakeSleepSeconds":1320,"unmeasurableSeconds":0,"spo2SleepSummary":{"userProfilePk":1520967,"deviceId":3359304790,"sleepMeasurementStartGMT":"2021-10-23T03:47:00.0","sleepMeasurementEndGMT":"2021-10-23T12:51:00.0","averageSPO2":92.0,"averageHR":53.0,"lowestSPO2":83},"averageRespiration":16.0,"lowestRespiration":9.0,"highestRespiration":23.0,"retro":false,"awakeCount":2,"avgSleepStress":13.71743119266055,"sleepScores":{"overallScore":80,"qualityScore":72,"durationScore":100,"recoveryScore":85,"deepScore":10,"remScore":66,"lightScore":16,"awakeningsCountScore":75,"awakeTimeScore":78,"combinedAwakeScore":76,"restfulnessScore":66,"feedback":"POSITIVE_LONG_AND_RECOVERING","insight":"POSITIVE_ACCLIMATIZATION_IN_PROGRESS"}},{"sleepStartTimestampGMT":"2021-10-24T04:11:00.0","sleepEndTimestampGMT":"2021-10-24T14:16:00.0","calendarDate":"2021-10-24","sleepWindowConfirmationType":"ENHANCED_CONFIRMED_FINAL","deepSleepSeconds":0,"lightSleepSeconds":24480,"remSleepSeconds":10500,"awakeSleepSeconds":1320,"unmeasurableSeconds":0,"spo2SleepSummary":{"userProfilePk":1520967,"deviceId":3359304790,"sleepMeasurementStartGMT":"2021-10-24T04:12:00.0","sleepMeasurementEndGMT":"2021-10-24T13:32:00.0","averageSPO2":92.0,"averageHR":55.0,"lowestSPO2":83},"averageRespiration":14.0,"lowestRespiration":10.0,"highestRespiration":21.0,"retro":false,"awakeCount":1,"avgSleepStress":10.224080267558529,"sleepScores":{"overallScore":86,"qualityScore":79,"durationScore":100,"recoveryScore":96,"deepScore":0,"remScore":83,"lightScore":65,"awakeningsCountScore":87,"awakeTimeScore":78,"combinedAwakeScore":82,"restfulnessScore":63,"feedback":"NEGATIVE_LONG_BUT_LIGHT","insight":"NEGATIVE_ACCLIMATIZATION_IN_PROGRESS"}},{"sleepStartTimestampGMT":"2021-10-25T04:21:00.0","sleepEndTimestampGMT":"2021-10-25T12:40:00.0","calendarDate":"2021-10-25","sleepWindowConfirmationType":"ENHANCED_CONFIRMED_FINAL","deepSleepSeconds":2220,"lightSleepSeconds":19620,"remSleepSeconds":7620,"awakeSleepSeconds":480,"unmeasurableSeconds":0,"spo2SleepSummary":{"userProfilePk":1520967,"deviceId":3359304790,"sleepMeasurementStartGMT":"2021-10-25T04:22:00.0","sleepMeasurementEndGMT":"2021-10-25T12:40:00.0","averageSPO2":93.0,"averageHR":51.0,"lowestSPO2":86},"averageRespiration":16.0,"lowestRespiration":11.0,"highestRespiration":21.0,"retro":false,"awakeCount":1,"avgSleepStress":7.488843813387424,"sleepScores":{"overallScore":92,"qualityScore":88,"durationScore":100,"recoveryScore":100,"deepScore":33,"remScore":100,"lightScore":72,"awakeningsCountScore":87,"awakeTimeScore":95,"combinedAwakeScore":91,"restfulnessScore":69,"feedback":"POSITIVE_LONG_AND_RECOVERING","insight":"POSITIVE_ACCLIMATIZATION_IN_PROGRESS"}},{"sleepStartTimestampGMT":"2021-10-26T03:44:00.0","sleepEndTimestampGMT":"2021-10-26T12:42:00.0","calendarDate":"2021-10-26","sleepWindowConfirmationType":"ENHANCED_CONFIRMED_FINAL","deepSleepSeconds":1980,"lightSleepSeconds":19560,"remSleepSeconds":9420,"awakeSleepSeconds":1320,"unmeasurableSeconds":0,"spo2SleepSummary":{"userProfilePk":1520967,"deviceId":3359304790,"sleepMeasurementStartGMT":"2021-10-26T03:45:00.0","sleepMeasurementEndGMT":"2021-10-26T12:41:00.0","averageSPO2":93.0,"averageHR":50.0,"lowestSPO2":83},"averageRespiration":15.0,"lowestRespiration":8.0,"highestRespiration":22.0,"retro":false,"awakeCount":2,"avgSleepStress":7.5,"sleepScores":{"overallScore":88,"qualityScore":82,"durationScore":100,"recoveryScore":100,"deepScore":19,"remScore":80,"lightScore":79,"awakeningsCountScore":75,"awakeTimeScore":78,"combinedAwakeScore":76,"restfulnessScore":65,"feedback":"POSITIVE_LONG_AND_RECOVERING","insight":"POSITIVE_ACCLIMATIZATION_IN_PROGRESS"}},{"sleepStartTimestampGMT":"2021-10-27T04:31:00.0","sleepEndTimestampGMT":"2021-10-27T12:42:00.0","calendarDate":"2021-10-27","sleepWindowConfirmationType":"ENHANCED_CONFIRMED_FINAL","deepSleepSeconds":2040,"lightSleepSeconds":20100,"remSleepSeconds":7020,"awakeSleepSeconds":300,"unmeasurableSeconds":0,"spo2SleepSummary":{"userProfilePk":1520967,"deviceId":3359304790,"sleepMeasurementStartGMT":"2021-10-27T04:32:00.0","sleepMeasurementEndGMT":"2021-10-27T12:42:00.0","averageSPO2":93.0,"averageHR":51.0,"lowestSPO2":85},"averageRespiration":15.0,"lowestRespiration":9.0,"highestRespiration":21.0,"retro":false,"awakeCount":0,"avgSleepStress":7.8979591836734695,"sleepScores":{"overallScore":93,"qualityScore":90,"durationScore":100,"recoveryScore":100,"deepScore":27,"remScore":100,"lightScore":67,"awakeningsCountScore":100,"awakeTimeScore":100,"combinedAwakeScore":100,"restfulnessScore":70,"feedback":"POSITIVE_HIGHLY_RECOVERING","insight":"POSITIVE_ACCLIMATIZATION_IN_PROGRESS"}},{"sleepStartTimestampGMT":"2021-10-28T04:45:00.0","sleepEndTimestampGMT":"2021-10-28T11:46:00.0","calendarDate":"2021-10-28","sleepWindowConfirmationType":"ENHANCED_CONFIRMED_FINAL","deepSleepSeconds":2520,"lightSleepSeconds":18060,"remSleepSeconds":4680,"awakeSleepSeconds":0,"unmeasurableSeconds":0,"spo2SleepSummary":{"userProfilePk":1520967,"deviceId":3359304790,"sleepMeasurementStartGMT":"2021-10-28T04:46:00.0","sleepMeasurementEndGMT":"2021-10-28T11:46:00.0","averageSPO2":93.0,"averageHR":49.0,"lowestSPO2":86},"averageRespiration":14.0,"lowestRespiration":8.0,"highestRespiration":21.0,"retro":false,"awakeCount":0,"avgSleepStress":7.146282973621103,"sleepScores":{"overallScore":87,"qualityScore":92,"durationScore":78,"recoveryScore":100,"deepScore":62,"remScore":73,"lightScore":62,"awakeningsCountScore":100,"awakeTimeScore":100,"combinedAwakeScore":100,"restfulnessScore":81,"feedback":"POSITIVE_RECOVERING","insight":"POSITIVE_ACCLIMATIZATION_IN_PROGRESS"}},{"sleepStartTimestampGMT":"2021-10-29T04:45:00.0","sleepEndTimestampGMT":"2021-10-29T12:37:00.0","calendarDate":"2021-10-29","sleepWindowConfirmationType":"ENHANCED_CONFIRMED_FINAL","deepSleepSeconds":1380,"lightSleepSeconds":21360,"remSleepSeconds":5220,"awakeSleepSeconds":360,"unmeasurableSeconds":0,"spo2SleepSummary":{"userProfilePk":1520967,"deviceId":3359304790,"sleepMeasurementStartGMT":"2021-10-29T04:47:00.0","sleepMeasurementEndGMT":"2021-10-29T12:37:00.0","averageSPO2":94.0,"averageHR":50.0,"lowestSPO2":87},"averageRespiration":15.0,"lowestRespiration":9.0,"highestRespiration":21.0,"retro":false,"awakeCount":1,"avgSleepStress":7.754310344827586,"sleepScores":{"overallScore":86,"qualityScore":82,"durationScore":95,"recoveryScore":100,"deepScore":0,"remScore":74,"lightScore":29,"awakeningsCountScore":87,"awakeTimeScore":99,"combinedAwakeScore":93,"restfulnessScore":64,"feedback":"POSITIVE_LONG_AND_RECOVERING","insight":"POSITIVE_ACCLIMATIZATION_IN_PROGRESS"}},{"sleepStartTimestampGMT":"2021-10-30T04:41:00.0","sleepEndTimestampGMT":"2021-10-30T14:45:00.0","calendarDate":"2021-10-30","sleepWindowConfirmationType":"ENHANCED_CONFIRMED_FINAL","deepSleepSeconds":0,"lightSleepSeconds":27900,"remSleepSeconds":8340,"awakeSleepSeconds":0,"unmeasurableSeconds":0,"spo2SleepSummary":{"userProfilePk":1520967,"deviceId":3359304790,"sleepMeasurementStartGMT":"2021-10-30T04:42:00.0","sleepMeasurementEndGMT":"2021-10-30T13:32:00.0","averageSPO2":93.0,"averageHR":54.0,"lowestSPO2":87},"averageRespiration":15.0,"lowestRespiration":11.0,"highestRespiration":23.0,"retro":false,"awakeCount":0,"avgSleepStress":8.820299500831947,"sleepScores":{"overallScore":92,"qualityScore":88,"durationScore":100,"recoveryScore":100,"deepScore":0,"remScore":97,"lightScore":24,"awakeningsCountScore":100,"awakeTimeScore":100,"combinedAwakeScore":100,"restfulnessScore":80,"feedback":"POSITIVE_LONG_AND_RECOVERING","insight":"POSITIVE_ACCLIMATIZATION_IN_PROGRESS"}},{"sleepStartTimestampGMT":"2021-10-31T04:10:00.0","sleepEndTimestampGMT":"2021-10-31T13:19:00.0","calendarDate":"2021-10-31","sleepWindowConfirmationType":"ENHANCED_CONFIRMED_FINAL","deepSleepSeconds":1740,"lightSleepSeconds":22320,"remSleepSeconds":7560,"awakeSleepSeconds":1320,"unmeasurableSeconds":0,"spo2SleepSummary":{"userProfilePk":1520967,"deviceId":3359304790,"sleepMeasurementStartGMT":"2021-10-31T04:11:00.0","sleepMeasurementEndGMT":"2021-10-31T13:19:00.0","averageSPO2":93.0,"averageHR":52.0,"lowestSPO2":84},"averageRespiration":15.0,"lowestRespiration":12.0,"highestRespiration":20.0,"retro":false,"awakeCount":2,"avgSleepStress":7.406593406593407,"sleepScores":{"overallScore":87,"qualityScore":81,"durationScore":100,"recoveryScore":100,"deepScore":7,"remScore":100,"lightScore":64,"awakeningsCountScore":75,"awakeTimeScore":78,"combinedAwakeScore":76,"restfulnessScore":53,"feedback":"POSITIVE_LONG_AND_RECOVERING","insight":"POSITIVE_ACCLIMATIZATION_IN_PROGRESS"}},{"sleepStartTimestampGMT":"2021-11-01T04:36:00.0","sleepEndTimestampGMT":"2021-11-01T12:45:00.0","calendarDate":"2021-11-01","sleepWindowConfirmationType":"ENHANCED_CONFIRMED_FINAL","deepSleepSeconds":2280,"lightSleepSeconds":19560,"remSleepSeconds":6720,"awakeSleepSeconds":780,"unmeasurableSeconds":0,"spo2SleepSummary":{"userProfilePk":1520967,"deviceId":3359304790,"sleepMeasurementStartGMT":"2021-11-01T04:37:00.0","sleepMeasurementEndGMT":"2021-11-01T12:45:00.0","averageSPO2":94.0,"averageHR":52.0,"lowestSPO2":88},"averageRespiration":15.0,"lowestRespiration":10.0,"highestRespiration":21.0,"retro":false,"awakeCount":2,"avgSleepStress":8.9079754601227,"sleepScores":{"overallScore":92,"qualityScore":88,"durationScore":100,"recoveryScore":100,"deepScore":40,"remScore":100,"lightScore":68,"awakeningsCountScore":75,"awakeTimeScore":89,"combinedAwakeScore":82,"restfulnessScore":73,"feedback":"POSITIVE_LONG_AND_RECOVERING","insight":"POSITIVE_ACCLIMATIZATION_IN_PROGRESS"}},{"sleepStartTimestampGMT":"2021-11-02T04:05:00.0","sleepEndTimestampGMT":"2021-11-02T12:37:00.0","calendarDate":"2021-11-02","sleepWindowConfirmationType":"ENHANCED_CONFIRMED_FINAL","deepSleepSeconds":4020,"lightSleepSeconds":16260,"remSleepSeconds":9480,"awakeSleepSeconds":960,"unmeasurableSeconds":0,"spo2SleepSummary":{"userProfilePk":1520967,"deviceId":3359304790,"sleepMeasurementStartGMT":"2021-11-02T04:08:00.0","sleepMeasurementEndGMT":"2021-11-02T12:37:00.0","averageSPO2":93.0,"averageHR":49.0,"lowestSPO2":83},"averageRespiration":15.0,"lowestRespiration":10.0,"highestRespiration":21.0,"retro":false,"awakeCount":1,"avgSleepStress":7.092885375494071,"sleepScores":{"overallScore":93,"qualityScore":89,"durationScore":100,"recoveryScore":100,"deepScore":73,"remScore":75,"lightScore":100,"awakeningsCountScore":87,"awakeTimeScore":85,"combinedAwakeScore":86,"restfulnessScore":68,"feedback":"POSITIVE_HIGHLY_RECOVERING","insight":"POSITIVE_ACCLIMATIZATION_IN_PROGRESS"}},{"sleepStartTimestampGMT":"2021-11-03T04:54:00.0","sleepEndTimestampGMT":"2021-11-03T12:07:00.0","calendarDate":"2021-11-03","sleepWindowConfirmationType":"ENHANCED_CONFIRMED_FINAL","deepSleepSeconds":2220,"lightSleepSeconds":20460,"remSleepSeconds":3300,"awakeSleepSeconds":0,"unmeasurableSeconds":0,"spo2SleepSummary":{"userProfilePk":1520967,"deviceId":3359304790,"sleepMeasurementStartGMT":"2021-11-03T04:55:00.0","sleepMeasurementEndGMT":"2021-11-03T12:07:00.0","averageSPO2":93.0,"averageHR":51.0,"lowestSPO2":84},"averageRespiration":16.0,"lowestRespiration":11.0,"highestRespiration":22.0,"retro":false,"awakeCount":0,"avgSleepStress":9.209677419354838,"sleepScores":{"overallScore":85,"qualityScore":87,"durationScore":82,"recoveryScore":100,"deepScore":47,"remScore":36,"lightScore":10,"awakeningsCountScore":100,"awakeTimeScore":100,"combinedAwakeScore":100,"restfulnessScore":83,"feedback":"POSITIVE_LONG_AND_RECOVERING","insight":"POSITIVE_ACCLIMATIZATION_IN_PROGRESS"}}]